{
  "logNo": "222064736439",
  "title": "구안와사(안면신경마비) 원인과 치료",
  "addDate": "2020. 8. 19.",
  "categoryNo": "12",
  "parentCategoryNo": "7",
  "url": "https://blog.naver.com/PostView.naver?blogId=isuhani&logNo=222064736439",
  "html_size": 209558,
  "body": "<div class=\"se-main-container\">\n                <div class=\"se-component se-text se-l-default\" id=\"SE-23335cd6-85be-4ee7-a0db-802b26f1e21b\">\n                    <div class=\"se-component-content\">\n                        <div class=\"se-section se-section-text se-l-default\">\n                            <div class=\"se-module se-module-text\">\n\n                                    <!-- SE-TEXT { --><p class=\"se-text-paragraph se-text-paragraph-align- \" style=\"\" id=\"SE-f2317614-5453-4b03-8761-19b37ffe9b84\"><span style=\"\" class=\"se-fs- se-ff-   \" id=\"SE-efaf5dbd-1d4d-48d9-beb0-04c457a33ed4\">한의학에서는 중풍(中風 - 뇌졸중)을 그 심한 정도에 따라 여러가지 단계로 나눕니다. 구안와사는 그 중에서 비교적 가벼운 단계인 중혈맥(中血脈)에 해당한다고 분류했죠. </span></p><!-- } SE-TEXT --><!-- SE-TEXT { --><p class=\"se-text-paragraph se-text-paragraph-align- \" style=\"\" id=\"SE-fa18d521-3378-4228-b701-0f166b1f9a3b\"><span style=\"\" class=\"se-fs- se-ff-   \" id=\"SE-2ad203ac-329d-4075-93f7-e3911117f74f\">​</span></p><!-- } SE-TEXT --><!-- SE-TEXT { --><p class=\"se-text-paragraph se-text-paragraph-align- \" style=\"\" id=\"SE-0de8dc20-a0bb-48b7-a46f-11bb3f8bfec1\"><span style=\"\" class=\"se-fs- se-ff-   \" id=\"SE-9de91245-fbc1-4b14-82a7-fb695a4a4f0c\"><i>(풍(風)이 혈맥에 맞으면 구안와사가 되고, 육부(六腑)에 맞으면 사지와 관절을 쓰지 못하고, 오장(五臟)에 맞으면 생명이 위태롭다) - 동의보감(동의보감출판사)-</i></span></p><!-- } SE-TEXT --><!-- SE-TEXT { --><p class=\"se-text-paragraph se-text-paragraph-align- \" style=\"\" id=\"SE-07e4f7ca-9ea1-4dfd-b439-54a069cc23e9\"><span style=\"\" class=\"se-fs- se-ff-   \" id=\"SE-aaf051b8-ba51-4094-ade3-dcf2be0fec18\">​</span></p><!-- } SE-TEXT --><!-- SE-TEXT { --><p class=\"se-text-paragraph se-text-paragraph-align- \" style=\"\" id=\"SE-56d108d2-526d-42c2-9c7a-9d9e063de828\"><span style=\"\" class=\"se-fs- se-ff-   \" id=\"SE-309ea651-61a5-4f31-aec7-a6e78f099fe7\">즉, 일반적인 구안와사는 생명이 위태롭지 않고, 팔다리와 관절에 마비가 발생하지 않는다는거죠. </span></p><!-- } SE-TEXT --><!-- SE-TEXT { --><p class=\"se-text-paragraph se-text-paragraph-align- \" style=\"\" id=\"SE-1c6d39d3-e22b-43b2-8b33-325f26f8e4ec\"><span style=\"\" class=\"se-fs- se-ff-   \" id=\"SE-251060a9-a5be-49e4-bd24-7cde511c5e72\">환자분들 중에는 얼굴 감각이 이상해지고, (한 쪽) 입술과 눈이 움직여지지 않기 시작하니 더 심해져서 반신마비가 되거나 의식장애까지 진행될꺼라는 공포를 느끼는 경우가 있습니다. 연구보고에 따르면 전체 구안와사 중 약 1% 정도는 중추성 원인이기에 실제로 반신마비로 진행될 수도 있습니다. 하지만, 숙련된 한의사라면 구안와사 질환을 진료할 때, 반신마비 등으로 진행 될 수 있는 중추성 구안와사는 감별진단이 되기때문에 안심해도 되겠습니다. </span></p><!-- } SE-TEXT -->\n                            </div>\n                        </div>\n                    </div>\n                </div>                <div class=\"se-component se-image se-l-default\" id=\"SE-38c51359-7554-4082-8841-9268c87f8c2c\">\n                    <div class=\"se-component-content se-component-content-fit\">\n                        <div class=\"se-section se-section-image se-l-default se-section-align-\" >\n\n                                <div class=\"se-module se-module-image\" style=\"\">\n                                    <a href=\"#\" class=\"se-module-image-link __se_image_link __se_link\" style=\"\" onclick=\"return false;\" data-linktype=\"img\" data-linkdata='{\"id\" : \"SE-38c51359-7554-4082-8841-9268c87f8c2c\", \"src\" : \"https://www.ebmconsult.com/app/article/images/100030\", \"linkUse\" : \"false\", \"link\" : \"\"}'>\n                                        <img src=\"https://www.ebmconsult.com/app/article/images/100030\" alt=\"\" class=\"se-image-resource\" />\n                                    </a>\n                                </div>\n                            <div class=\"se-module se-module-text se-caption\"><p class=\"se-text-paragraph se-text-paragraph-align- \" style=\"\" id=\"SE-6d5d011f-c19f-41fa-8d56-4eed2de2c2c6\"><span style=\"\" class=\"se-fs- se-ff-   \" id=\"SE-e6edeed8-4e51-4819-a955-f90ffb2d9b2b\">말초성구안와사 (안면신경마비)                                 중추성구안와사(뇌병변)</span></p></div>\n                        </div>\n                    </div>\n                </div>\n                <div class=\"se-component se-text se-l-default\" id=\"SE-6c4e2537-7e76-4026-b3a1-4b7d826ecd26\">\n                    <div class=\"se-component-content\">\n                        <div class=\"se-section se-section-text se-l-default\">\n                            <div class=\"se-module se-module-text\">\n\n                                    <!-- SE-TEXT { --><p class=\"se-text-paragraph se-text-paragraph-align- \" style=\"\" id=\"SE-45bb7316-e99b-4638-a28e-0b92d980077e\"><span style=\"\" class=\"se-fs- se-ff-   \" id=\"SE-397d5767-600f-4f48-89d3-9dc0b0924723\">​</span></p><!-- } SE-TEXT --><!-- SE-TEXT { --><p class=\"se-text-paragraph se-text-paragraph-align- \" style=\"\" id=\"SE-a8d18065-92e6-42e1-a46c-0e5bf62f75d5\"><span style=\"\" class=\"se-fs- se-ff-   \" id=\"SE-f86dddbb-6cae-4b89-8961-9d26472be789\">해부학과 진단기기의 발달로 현재는 구안와사(안면신경마비)의 원인이 바이러스&#x27; virus&#x27;라는게 밝혀졌습니다. </span></p><!-- } SE-TEXT --><!-- SE-TEXT { --><p class=\"se-text-paragraph se-text-paragraph-align- \" style=\"\" id=\"SE-b5e3688c-8a1b-46a8-ba02-0986de4963a2\"><span style=\"\" class=\"se-fs- se-ff-   \" id=\"SE-53f7b2df-125f-4e96-b221-e97573a9188c\">두개골 내</span><span style=\"color:#000000;\" class=\"se-fs- se-ff-   \" id=\"SE-e33a5754-2226-4e38-ba0a-1303740af9b6\"> </span><span style=\"color:#000000;\" class=\"se-fs-fs15 se-ff-  se-style-unset \" id=\"SE-48773df5-c4fb-4610-8625-1f7c568160a7\">슬상 신경절(geniculate ganglion)에 잠복되어 있던 헤르페스 바이러스의 재활성화(reactivation)가 </span><span style=\"color:#000000;\" class=\"se-fs- se-ff-   \" id=\"SE-5dae1403-3869-4210-91a2-1ea00a6140c3\"> 안면신경(facial nerve)</span><span style=\"color:#000000;\" class=\"se-fs-fs15 se-ff-  se-style-unset \" id=\"SE-1464332a-c58e-40c5-a5a8-c6a6cb6df7b1\">의 부종을 유발하는 것이 구안와사(안면신경바미)의 주된 원인으로 여겨지고 있습니다. </span></p><!-- } SE-TEXT -->\n                            </div>\n                        </div>\n                    </div>\n                </div>                <div class=\"se-component se-image se-l-default\" id=\"SE-a8f169f1-10a4-4588-8e63-fd130f8b4901\">\n                    <div class=\"se-component-content se-component-content-fit\">\n                        <div class=\"se-section se-section-image se-l-default se-section-align-\" >\n\n                                <div class=\"se-module se-module-image\" style=\"\">\n                                    <a href=\"#\" class=\"se-module-image-link __se_image_link __se_link\" style=\"\" onclick=\"return false;\" data-linktype=\"img\" data-linkdata='{\"id\" : \"SE-a8f169f1-10a4-4588-8e63-fd130f8b4901\", \"src\" : \"https://www.daviddarling.info/images/Bells_palsy.gif\", \"linkUse\" : \"false\", \"link\" : \"\"}'>\n                                        <img src=\"https://www.daviddarling.info/images/Bells_palsy.gif\" alt=\"\" class=\"se-image-resource\" />\n                                    </a>\n                                </div>\n                            <div class=\"se-module se-module-text se-caption\"><p class=\"se-text-paragraph se-text-paragraph-align- \" style=\"\" id=\"SE-d728ea1b-c613-4a4b-96b0-8ca86a85e9fc\"><span style=\"\" class=\"se-fs- se-ff-   \" id=\"SE-fb424aeb-2113-46f7-9cf4-8f76ecebe567\">얼굴로 가는 안면신경(facial nerve)가 귓구멍 근처에서 마비가 된다</span></p></div>\n                        </div>\n                    </div>\n                </div>\n                <div class=\"se-component se-text se-l-default\" id=\"SE-d0eae186-bc8c-4150-89a1-0cfe9a08c193\">\n                    <div class=\"se-component-content\">\n                        <div class=\"se-section se-section-text se-l-default\">\n                            <div class=\"se-module se-module-text\">\n\n                                    <!-- SE-TEXT { --><p class=\"se-text-paragraph se-text-paragraph-align- \" style=\"\" id=\"SE-26b4ab23-de53-44bd-a448-043a25a05965\"><span style=\"color:#000000;\" class=\"se-fs-fs15 se-ff-  se-style-unset \" id=\"SE-9360053e-1a7a-44ec-a114-b28889a3c131\">​</span></p><!-- } SE-TEXT --><!-- SE-TEXT { --><p class=\"se-text-paragraph se-text-paragraph-align- \" style=\"\" id=\"SE-07a57302-75e7-470d-b36b-42308dfc42b5\"><span style=\"color:#000000;\" class=\"se-fs-fs15 se-ff-  se-style-unset \" id=\"SE-7477fb9d-af52-42cb-b97e-22cb4afd678d\">안면신경이 부으면서 마비가 발생하면, 이후에 신경손상이 진행됩니다. 이러한 신경손상을 월러 변성(wallerian degeneration) 이라 하는데, 이 월러 변성이  심할수록 구안와사의 정도가 심해지고, 후유증의 가능성도 높아지겠죠. 월러 변성(wallerian degeneration)은 마비가 시작된 약 2일 후부터 14일까지 진행이 됩니다.</span></p><!-- } SE-TEXT -->\n                            </div>\n                        </div>\n                    </div>\n                </div>                <div class=\"se-component se-image se-l-default\" id=\"SE-817aa495-571f-4946-95e0-04f06a685b7a\">\n                    <div class=\"se-component-content se-component-content-fit\">\n                        <div class=\"se-section se-section-image se-l-default se-section-align-\" >\n\n                                <div class=\"se-module se-module-image\" style=\"\">\n                                    <a href=\"#\" class=\"se-module-image-link __se_image_link __se_link\" style=\"\" onclick=\"return false;\" data-linktype=\"img\" data-linkdata='{\"id\" : \"SE-817aa495-571f-4946-95e0-04f06a685b7a\", \"src\" : \"https://www.researchgate.net/profile/Carla_Baan/publication/336214881/figure/fig2/AS:872237502582785@1584969034212/Schematic-drawing-of-Wallerian-degeneration-following-peripheral-nerve-injury-a.png\", \"linkUse\" : \"false\", \"link\" : \"\"}'>\n                                        <img src=\"https://www.researchgate.net/profile/Carla_Baan/publication/336214881/figure/fig2/AS:872237502582785@1584969034212/Schematic-drawing-of-Wallerian-degeneration-following-peripheral-nerve-injury-a.png\" alt=\"\" class=\"se-image-resource\" />\n                                    </a>\n                                </div>\n                            <div class=\"se-module se-module-text se-caption\"><p class=\"se-text-paragraph se-text-paragraph-align- \" style=\"\" id=\"SE-fc05ad54-9cf0-4dcd-9e25-1887c8ec22f9\"><span style=\"\" class=\"se-fs- se-ff-   \" id=\"SE-1ca7545b-17bb-41de-8685-4a7c42dcc97f\">월러 변성 (wallerian degenertaion)</span></p></div>\n                        </div>\n                    </div>\n                </div>\n                <div class=\"se-component se-text se-l-default\" id=\"SE-fd55d92b-02b4-40f9-b340-8bcc4e1ce384\">\n                    <div class=\"se-component-content\">\n                        <div class=\"se-section se-section-text se-l-default\">\n                            <div class=\"se-module se-module-text\">\n\n                                    <!-- SE-TEXT { --><p class=\"se-text-paragraph se-text-paragraph-align- \" style=\"\" id=\"SE-77afe0d1-3705-482c-a57a-f4cb114d904a\"><span style=\"color:#000000;\" class=\"se-fs-fs15 se-ff-  se-style-unset \" id=\"SE-eee18920-1b9d-443a-891c-05169b9208de\">​</span></p><!-- } SE-TEXT --><!-- SE-TEXT { --><p class=\"se-text-paragraph se-text-paragraph-align- \" style=\"\" id=\"SE-2e779f49-9e7b-4ff7-8b96-7eeee1979001\"><span style=\"\" class=\"se-fs- se-ff-   \" id=\"SE-1ebd9184-8055-415f-94a2-b26b2941a131\">그렇기 때문에 구안와사(안면신경마비)가 발병하면 최대한 빨리 치료를 시작해야 합니다. 마비 다음날부터 신경손상이 2주동안 진행이 되잖아요. 마비 시작 2일째부터 14일까지 진행되는 신경손상을 최대한 줄여줘야 이후의 치료가 쉽고 후유증 없이 완치 될 수 있는겁니다. </span></p><!-- } SE-TEXT --><!-- SE-TEXT { --><p class=\"se-text-paragraph se-text-paragraph-align- \" style=\"\" id=\"SE-ca7a6fc2-4856-4204-82ce-11977025fcef\"><span style=\"\" class=\"se-fs- se-ff-   \" id=\"SE-dd85c868-130c-4a61-b89e-14716f21f05d\">구안와사(안면신경마비) 환자의 약 15~20%는 회복이 불완전하게 되어 후유증을 격게 된다고 합니다. 5명 중 1명은 후유증으로 평생 고생하게 되는거죠. 구안와사의 후유증은 얼굴에 드러나기 때문에 거울을 볼 때마다 스트레스를 받고, 사람들이 알아볼꺼라는 걱정에 대인기피 경향이 생기기도 합니다. </span></p><!-- } SE-TEXT --><!-- SE-TEXT { --><p class=\"se-text-paragraph se-text-paragraph-align- \" style=\"\" id=\"SE-9877d837-ea3a-47c5-8e05-e4587ae88c56\"><span style=\"\" class=\"se-fs- se-ff-   \" id=\"SE-203fb758-54bd-406f-9b40-8f75e21136fc\">후유증은 주로 마비가 완전히 치료되지 못해 눈, 볼, 입술 등의 움직임이 부자연스럽거나, 양쪽 얼굴의 비대칭이 발생합니다. 신경 회복과정에서 다른 신경과 혼선이 생기면 입술을 움직일 때마다 눈꺼풀이 같이 움직이는 등의 운동장애 증상이 발생하기도 합니다. </span></p><!-- } SE-TEXT --><!-- SE-TEXT { --><p class=\"se-text-paragraph se-text-paragraph-align- \" style=\"\" id=\"SE-0da6ce3a-ceba-44d4-9d3c-04c4945a4c56\"><span style=\"\" class=\"se-fs- se-ff-   \" id=\"SE-9af0ab97-0836-42da-bf95-1f6e1ec6940e\">​</span></p><!-- } SE-TEXT --><!-- SE-TEXT { --><p class=\"se-text-paragraph se-text-paragraph-align- \" style=\"\" id=\"SE-781f4c45-ca57-4351-8fbb-4e60ecae5cad\"><span style=\"\" class=\"se-fs- se-ff-   \" id=\"SE-0fdead3a-c35c-462b-8271-2a9291ee1e5f\">한국에서 매년 발생하는 구안와사(안면신경마비) 환자는 2016년 기준 대략 6만명 정도 된다고 합니다. 통계를 통해 추산해보면, 매년 6만명 중 20%인 1만2천명은 후유증이 남는겁니다. </span></p><!-- } SE-TEXT --><!-- SE-TEXT { --><p class=\"se-text-paragraph se-text-paragraph-align- \" style=\"\" id=\"SE-1199e598-325a-4021-8f83-ae3f34e6eac9\"><span style=\"\" class=\"se-fs- se-ff-   \" id=\"SE-4932d30a-93e3-4115-82f3-9d96f06c14c2\">중혈맥(中血脈)이라 팔다리의 마비나 생명의 위험은 없지만, 결코 무시할 수 없는 질병이죠. </span></p><!-- } SE-TEXT --><!-- SE-TEXT { --><p class=\"se-text-paragraph se-text-paragraph-align- \" style=\"\" id=\"SE-9a0c087b-49d2-4b28-8358-ba582e311982\"><span style=\"\" class=\"se-fs- se-ff-   \" id=\"SE-69f2fe9d-7f94-4a6a-83eb-0fede305c827\">​</span></p><!-- } SE-TEXT --><!-- SE-TEXT { --><p class=\"se-text-paragraph se-text-paragraph-align- \" style=\"\" id=\"SE-38aba014-1a1c-411a-b7bb-00066102c511\"><span style=\"\" class=\"se-fs- se-ff-   \" id=\"SE-bde64897-dc96-4226-92b7-79022da25f3a\">구안와사(안면신경마비)의 치료는 어떻게 해야 할까요?</span></p><!-- } SE-TEXT --><!-- SE-TEXT { --><p class=\"se-text-paragraph se-text-paragraph-align- \" style=\"\" id=\"SE-73d22791-d180-4bd3-98dc-9671af17bd20\"><span style=\"\" class=\"se-fs- se-ff-   \" id=\"SE-ead945db-6e1b-4d46-9559-8b62bbd7d398\">가장 중요한 것은 !!!   시간!!!! 입니다. </span></p><!-- } SE-TEXT --><!-- SE-TEXT { --><p class=\"se-text-paragraph se-text-paragraph-align- \" style=\"\" id=\"SE-f6f77d45-ba26-4bf5-948c-aeb1548dd0e5\"><span style=\"\" class=\"se-fs- se-ff-   \" id=\"SE-66bb8b41-2790-41ff-99b3-4e4fb4bfaa2b\">얼굴 감각이 이상하다, 입술이 잘 안움직여지는 것 같다, 눈을 뜨고 감는게 어색하게 느껴질 때에는 바로 진료를 받고 치료를 시작해야 합니다. </span></p><!-- } SE-TEXT --><!-- SE-TEXT { --><p class=\"se-text-paragraph se-text-paragraph-align- \" style=\"\" id=\"SE-56092032-16de-4372-8c73-8573c66a9c7c\"><span style=\"\" class=\"se-fs- se-ff-   \" id=\"SE-0079a08f-4bc3-472b-8c77-cc07523731a8\">신속히 치료해서 안면신경의 부종을 막을 수 있으면 신경변성을 예방할 수 있고, 당연히 안면마비 증상이 경미하게 있다가 사라질 수도 있습니다. </span></p><!-- } SE-TEXT --><!-- SE-TEXT { --><p class=\"se-text-paragraph se-text-paragraph-align- \" style=\"\" id=\"SE-67204bde-660d-4aaa-8e5c-3b321485b7d5\"><span style=\"\" class=\"se-fs- se-ff-   \" id=\"SE-a650dc4b-60b5-4a4a-96cb-67f89a915c21\">시간이 지체되어 안면신경 부종을 막지 못했다면 신경의 월러 변성(wallerian degenertion) 과정을 최대한 막아야 합니다. </span></p><!-- } SE-TEXT --><!-- SE-TEXT { --><p class=\"se-text-paragraph se-text-paragraph-align- \" style=\"\" id=\"SE-3f6b6d55-b103-4cc6-864e-e2d1136f517b\"><span style=\"\" class=\"se-fs- se-ff-   \" id=\"SE-1a27d05f-f06a-494e-9d4d-a40af79fc0b0\">​</span></p><!-- } SE-TEXT --><!-- SE-TEXT { --><p class=\"se-text-paragraph se-text-paragraph-align- \" style=\"\" id=\"SE-382f3ce8-1df1-4cbd-a05e-c3b49addf30b\"><span style=\"\" class=\"se-fs- se-ff-   \" id=\"SE-d2600413-9a03-4a78-9dd1-310002fe0b36\">그래서 구안와사(안면신경마비) 발병일 혹은 발병 뒷날부터 2주간은 급성기치료를 해야 합니다. 신경손상을 최대한 막는 치료를 해야죠</span></p><!-- } SE-TEXT --><!-- SE-TEXT { --><p class=\"se-text-paragraph se-text-paragraph-align- \" style=\"\" id=\"SE-dd86db76-ae72-41ac-afe8-f87bea3ac270\"><span style=\"\" class=\"se-fs- se-ff-   \" id=\"SE-d38e29ce-aab1-4a9d-9bfd-16709645831a\">한의원에서는 중혈맥(中血脈)의 치료에 맞게끔, 또한 신경손상을 억제하고 염증을 치료하기 위한 한약치료, 약침치료, 침치료를 합니다. </span></p><!-- } SE-TEXT --><!-- SE-TEXT { --><p class=\"se-text-paragraph se-text-paragraph-align- \" style=\"\" id=\"SE-5406098d-2bad-4b78-aa4a-49c81e20feae\"><span style=\"\" class=\"se-fs- se-ff-   \" id=\"SE-c9928fdb-e68a-4e67-9fa6-93c038df72c7\">​</span></p><!-- } SE-TEXT --><!-- SE-TEXT { --><p class=\"se-text-paragraph se-text-paragraph-align- \" style=\"\" id=\"SE-75e26a23-030e-4ab1-99d8-ce532a8732bb\"><span style=\"\" class=\"se-fs- se-ff-   \" id=\"SE-0c565cf7-5314-49d5-ba22-0a555c3c9d1d\">최근 양방병원에서는 초기에 스테로이드 약물치료법을 시행합니다. 2010년~2015년사이 안면신경마비(벨 마비)에 대한 코크란 리뷰(cochrane&#x27;s review - 의학 연구 논문들을 정리한 리뷰)에 따르면 안면신경마비에 대한 여러가지 치료 중 스테로이드 약물 치료법이 신경 부종을 감소시키고 신경손상을 줄여준다고 합니다. 그에 따라 발병 초기 약 5 일간의 스테로이드 약물 치료를 보편적으로 시행하죠. (스테로이드 약물의 특성 때문에 5일간 복용 후에도 서서히 약을 줄여가면서 몇 일 더 복용하게 합니다. 테이퍼링이라 하죠) </span></p><!-- } SE-TEXT --><!-- SE-TEXT { --><p class=\"se-text-paragraph se-text-paragraph-align- \" style=\"\" id=\"SE-ec751d58-387f-495d-93af-71944ee1739a\"><span style=\"\" class=\"se-fs- se-ff-   \" id=\"SE-c07880d7-8bf7-46f6-a23f-e7dcad5cd3ae\">Ramsey 등의 보고에 의하면 스테로이드 치료는 후유증의 확률을 17% 정도 줄여준다고 합니다. </span></p><!-- } SE-TEXT --><!-- SE-TEXT { --><p class=\"se-text-paragraph se-text-paragraph-align- \" style=\"\" id=\"SE-1188d2bf-78bf-4bbe-98d8-bca5c946e0cc\"><span style=\"\" class=\"se-fs- se-ff-   \" id=\"SE-f9398040-6d1e-4d57-ac7a-7437d395043f\">​</span></p><!-- } SE-TEXT -->\n                            </div>\n                        </div>\n                    </div>\n                </div>                <div class=\"se-component se-image se-l-default\" id=\"SE-87418984-a3e3-436f-bcce-3ed98459fa19\">\n                    <div class=\"se-component-content se-component-content-fit\">\n                        <div class=\"se-section se-section-image se-l-default se-section-align-\" >\n\n                                <div class=\"se-module se-module-image\" style=\"\">\n                                    <a href=\"#\" class=\"se-module-image-link __se_image_link __se_link\" style=\"\" onclick=\"return false;\" data-linktype=\"img\" data-linkdata='{\"id\" : \"SE-87418984-a3e3-436f-bcce-3ed98459fa19\", \"src\" : \"https://postfiles.pstatic.net/MjAyMDA4MTlfMjU5/MDAxNTk3ODA4ODA1Njgx.nPCU7ax6qcUlJvyIEkxuR18nl3iCcbmQK1t08m-hc74g.40eYMyzmAh2xGrakn80ZNPk3hcozw5faFgMClX0BMEog.PNG.isuhani/image.png\", \"linkUse\" : \"false\", \"link\" : \"\"}'>\n                                        <img src=\"https://postfiles.pstatic.net/MjAyMDA4MTlfMjU5/MDAxNTk3ODA4ODA1Njgx.nPCU7ax6qcUlJvyIEkxuR18nl3iCcbmQK1t08m-hc74g.40eYMyzmAh2xGrakn80ZNPk3hcozw5faFgMClX0BMEog.PNG.isuhani/image.png?type=w80_blur\" data-lazy-src=\"https://postfiles.pstatic.net/MjAyMDA4MTlfMjU5/MDAxNTk3ODA4ODA1Njgx.nPCU7ax6qcUlJvyIEkxuR18nl3iCcbmQK1t08m-hc74g.40eYMyzmAh2xGrakn80ZNPk3hcozw5faFgMClX0BMEog.PNG.isuhani/image.png?type=w580\" data-width=\"500\" data-height=\"107\" alt=\"\" class=\"se-image-resource\" />\n                                    </a>\n                                </div>\n                        </div>\n                    </div>\n                </div>\n                <div class=\"se-component se-text se-l-default\" id=\"SE-f376a720-de4d-4a18-8a4d-35997580cc15\">\n                    <div class=\"se-component-content\">\n                        <div class=\"se-section se-section-text se-l-default\">\n                            <div class=\"se-module se-module-text\">\n\n                                    <!-- SE-TEXT { --><p class=\"se-text-paragraph se-text-paragraph-align- \" style=\"\" id=\"SE-59cd5b32-f5c2-4470-911d-bdddfc985103\"><span style=\"\" class=\"se-fs- se-ff-   \" id=\"SE-801bb9b3-e654-4799-a4da-0e9a7f681f45\">​</span></p><!-- } SE-TEXT --><!-- SE-TEXT { --><p class=\"se-text-paragraph se-text-paragraph-align- \" style=\"\" id=\"SE-7c6d14d5-f91a-4d44-9a91-e5297aba2ca1\"><span style=\"\" class=\"se-fs- se-ff-   \" id=\"SE-b76aab07-67e5-4e66-824d-1d4b107330cd\">2주 이후부터 약 2~4주 동안은 회복기 치료를 해야 합니다. </span></p><!-- } SE-TEXT --><!-- SE-TEXT { --><p class=\"se-text-paragraph se-text-paragraph-align- \" style=\"\" id=\"SE-61c7569f-9d40-40b9-b7b0-3413efed13f4\"><span style=\"\" class=\"se-fs- se-ff-   \" id=\"SE-06c1a8ec-e330-49a7-b745-a70510703c17\">손상된 신경의 회복과, 마비된 안면 근육의 회복을 위해 모든 치료를 집중해야 합니다. 치료가 잘 되는 경우에는 2주이내에, 조금 늦어지더라도 4주 이내에 거의 완전히 회복이 될 수 있게끔 해야 합니다. 회복이 늦어지면 후유증 발생 가능성이 높아집니다. </span></p><!-- } SE-TEXT --><!-- SE-TEXT { --><p class=\"se-text-paragraph se-text-paragraph-align- \" style=\"\" id=\"SE-f68a47bd-efeb-440a-99a9-f159a3540b13\"><span style=\"\" class=\"se-fs- se-ff-   \" id=\"SE-537466dc-2f17-41ce-85f8-1b2d0d854a9a\">이수한의원에서는  혈맥을 통하게 하고 근육 마비를 치료하는 회복기 한약, 회복기 약침, 회복기 침치료를 시행합니다. </span></p><!-- } SE-TEXT --><!-- SE-TEXT { --><p class=\"se-text-paragraph se-text-paragraph-align- \" style=\"\" id=\"SE-9b5ef709-2ebc-4415-88ff-f015f57f3630\"><span style=\"\" class=\"se-fs- se-ff-   \" id=\"SE-a734cd86-c53a-4cb9-aa15-1301a76012c4\">양방에서는 각 의료기관마다 치료법이 다른 실정이고, 영양제 등을 처방하곤 합니다. </span></p><!-- } SE-TEXT --><!-- SE-TEXT { --><p class=\"se-text-paragraph se-text-paragraph-align- \" style=\"\" id=\"SE-dcad1908-e81e-4906-b744-dc385862ef63\"><span style=\"\" class=\"se-fs- se-ff-   \" id=\"SE-5803dbb7-56ed-4513-8d72-0512736abe60\">​</span></p><!-- } SE-TEXT --><!-- SE-TEXT { --><p class=\"se-text-paragraph se-text-paragraph-align- \" style=\"\" id=\"SE-325f66c9-368f-4525-abae-57597428ed10\"><span style=\"\" class=\"se-fs- se-ff-   \" id=\"SE-e0ef9993-6849-4bde-b317-f3c77fb6f648\">이후에는 환자분의 몸 상태에 따라 유지기 치료를 할 수도 있습니다. </span></p><!-- } SE-TEXT --><!-- SE-TEXT { --><p class=\"se-text-paragraph se-text-paragraph-align- \" style=\"\" id=\"SE-6e00f6c8-2ed5-4cdc-aa62-df88b2e31e7e\"><span style=\"color:#000000;background-color:#ffffff;\" class=\"se-fs- se-ff-  se-style-unset \" id=\"SE-2c3f76a1-fcc0-444a-8b50-7db774f51571\">한의학에서는 正氣存內 邪不可干(</span><span style=\"color:#000000;background-color:#ffffff;\" class=\"se-fs- se-ff-  se-style-unset \" id=\"SE-3796c365-4f8b-4808-aba0-2cb085e2c77e\"><b>정기존내 사불가간</b></span><span style=\"color:#000000;background-color:#ffffff;\" class=\"se-fs- se-ff-  se-style-unset \" id=\"SE-50a46a80-f7c4-4c19-ba5c-6228f6cf4fec\">)이라는 대전제가 있습니다. 내 몸의 기운이 바르고 충분하면, 병이 생기지 않는다는 것이죠. </span></p><!-- } SE-TEXT --><!-- SE-TEXT { --><p class=\"se-text-paragraph se-text-paragraph-align- \" style=\"\" id=\"SE-07132f78-348b-4422-989d-62296be3c64f\"><span style=\"color:#000000;background-color:#ffffff;\" class=\"se-fs- se-ff-  se-style-unset \" id=\"SE-3c724138-80ed-4276-b810-749b07112ab5\">중혈맥(中血脈)이 발생할 몸 상태였기 때문에 병이 생길 수 있었다고 봅니다. </span></p><!-- } SE-TEXT --><!-- SE-TEXT { --><p class=\"se-text-paragraph se-text-paragraph-align- \" style=\"\" id=\"SE-8173f262-35aa-4141-b45f-73f46bd7f431\"><span style=\"color:#000000;background-color:#ffffff;\" class=\"se-fs- se-ff-  se-style-unset \" id=\"SE-03c8764d-da55-4879-9a9d-e133bb3def16\">실제 구안와사 환자분들을 보면 발병할 당시 과로, 스트레스 등으로 심신이 약해진 상태였던 분들이 대다수죠. 심신이 약해지면 면역력이 약해지고 그로 인해 신경 주변에 바이러스가 염증을 유발하고 신견이 붓고 안면신경의 마비가 발생하는 겁니다. 구안와사(안면신경마비)의 치료기간 동안 치료 및 안정 이후에도 몸 상태가 완전회 회복되지 않은 경우에는 유지기 치료를 통해 정상 컨디션을 되찾고 유지시켜줘야 합니다. </span></p><!-- } SE-TEXT --><!-- SE-TEXT { --><p class=\"se-text-paragraph se-text-paragraph-align- \" style=\"\" id=\"SE-1d8e9940-bfb4-40e4-9cec-e1d234ee1589\"><span style=\"color:#000000;background-color:#ffffff;\" class=\"se-fs- se-ff-  se-style-unset \" id=\"SE-bdb6f49d-7411-43ef-a831-7e252125c7ea\">한약, 뇌신경추나요법, 침치료 등이 필요할 수 있습니다. </span></p><!-- } SE-TEXT --><!-- SE-TEXT { --><p class=\"se-text-paragraph se-text-paragraph-align- \" style=\"\" id=\"SE-b31d6115-51d5-4879-839f-0cf69ccac849\"><span style=\"color:#000000;\" class=\"se-fs- se-ff-  se-style-unset \" id=\"SE-3ef2cd60-71d2-49f5-8c02-9fadb1ce3078\">​</span></p><!-- } SE-TEXT --><!-- SE-TEXT { --><p class=\"se-text-paragraph se-text-paragraph-align- \" style=\"\" id=\"SE-5802667d-beef-470f-95bb-d5170230881c\"><span style=\"color:#000000;\" class=\"se-fs- se-ff-  se-style-unset \" id=\"SE-7300c54e-86c2-448f-b590-466390e41ee7\">​</span></p><!-- } SE-TEXT --><!-- SE-TEXT { --><p class=\"se-text-paragraph se-text-paragraph-align- \" style=\"\" id=\"SE-11710220-e3ca-4c2f-81b6-5de783732012\"><span style=\"color:#000000;background-color:#ffffff;\" class=\"se-fs- se-ff-  se-style-unset \" id=\"SE-decceabb-3e94-4616-b9a2-9347b574cf7c\">명심하세요. </span></p><!-- } SE-TEXT --><!-- SE-TEXT { --><p class=\"se-text-paragraph se-text-paragraph-align- \" style=\"\" id=\"SE-f32abd28-b39c-4b5b-927c-858662c9abd2\"><span style=\"color:#000000;background-color:#ffffff;\" class=\"se-fs- se-ff-  se-style-unset \" id=\"SE-f1662cdc-bf72-492c-98d6-326128b030ad\">구안와사가 의심되면, 최대한 빨리 의료기관을 방문하세요. </span></p><!-- } SE-TEXT --><!-- SE-TEXT { --><p class=\"se-text-paragraph se-text-paragraph-align- \" style=\"\" id=\"SE-0e331adf-eaf9-4828-a2ff-6e3ce078622d\"><span style=\"color:#000000;background-color:#ffffff;\" class=\"se-fs- se-ff-  se-style-unset \" id=\"SE-50af56c8-1c39-4831-857d-6f84030b331a\">이수한의원에 오시면 정확한 진단을 통해 급성기, 회복기, 필요에 따른 유지기 치료를 적절하게 받으실 수 있습니다. </span></p><!-- } SE-TEXT --><!-- SE-TEXT { --><p class=\"se-text-paragraph se-text-paragraph-align- \" style=\"\" id=\"SE-3c5ef5ff-c233-423c-92d4-e26a01d6e03b\"><span style=\"color:#000000;\" class=\"se-fs- se-ff-  se-style-unset \" id=\"SE-409c6c6e-7296-4225-9741-6aac65ac9299\">​</span></p><!-- } SE-TEXT -->\n                            </div>\n                        </div>\n                    </div>\n                </div>                <div class=\"se-component se-image se-l-default\" id=\"SE-81bf65ff-7d44-46c0-b4e9-c9af991b340e\">\n                    <div class=\"se-component-content se-component-content-fit\">\n                        <div class=\"se-section se-section-image se-l-default se-section-align-\" >\n\n                                <div class=\"se-module se-module-image\" style=\"\">\n                                    <a href=\"#\" class=\"se-module-image-link __se_image_link __se_link\" style=\"\" onclick=\"return false;\" data-linktype=\"img\" data-linkdata='{\"id\" : \"SE-81bf65ff-7d44-46c0-b4e9-c9af991b340e\", \"src\" : \"https://postfiles.pstatic.net/MjAyMDA4MTlfMTQ2/MDAxNTk3ODA4OTE3Mzcw.rxmZCN-aycZgvl1rFvVVMfcXYVKRXw8boZM48a46Blgg.xjwTvWgkeCq5JLOAaRIowwGWhoLcu9iLXigxatM_rfsg.PNG.isuhani/남성역_이수한의원.png\", \"linkUse\" : \"false\", \"link\" : \"\"}'>\n                                        <img src=\"https://postfiles.pstatic.net/MjAyMDA4MTlfMTQ2/MDAxNTk3ODA4OTE3Mzcw.rxmZCN-aycZgvl1rFvVVMfcXYVKRXw8boZM48a46Blgg.xjwTvWgkeCq5JLOAaRIowwGWhoLcu9iLXigxatM_rfsg.PNG.isuhani/남성역_이수한의원.png?type=w80_blur\" data-lazy-src=\"https://postfiles.pstatic.net/MjAyMDA4MTlfMTQ2/MDAxNTk3ODA4OTE3Mzcw.rxmZCN-aycZgvl1rFvVVMfcXYVKRXw8boZM48a46Blgg.xjwTvWgkeCq5JLOAaRIowwGWhoLcu9iLXigxatM_rfsg.PNG.isuhani/남성역_이수한의원.png?type=w580\" data-width=\"500\" data-height=\"597\" alt=\"\" class=\"se-image-resource\" />\n                                    </a>\n                                </div>\n                        </div>\n                    </div>\n                </div>\n                <div class=\"se-component se-text se-l-default\" id=\"SE-6a947414-00e2-4189-b92d-eb71271b73a3\">\n                    <div class=\"se-component-content\">\n                        <div class=\"se-section se-section-text se-l-default\">\n                            <div class=\"se-module se-module-text\">\n\n                                    <!-- SE-TEXT { --><p class=\"se-text-paragraph se-text-paragraph-align- \" style=\"\" id=\"SE-ca0391b8-cd94-44f9-aa96-66fdb12b4628\"><span style=\"color:#000000;\" class=\"se-fs- se-ff-  se-style-unset \" id=\"SE-1cac47e3-ec0a-4f1a-ac56-161d9c118d66\">​</span></p><!-- } SE-TEXT --><!-- SE-TEXT { --><p class=\"se-text-paragraph se-text-paragraph-align- \" style=\"\" id=\"SE-f4932726-89a2-43d1-b9ae-1eb98a44ca2f\"><span style=\"color:#000000;\" class=\"se-fs- se-ff-  se-style-unset \" id=\"SE-4b954e7c-27ab-4f12-993e-38077a411014\">​</span></p><!-- } SE-TEXT --><!-- SE-TEXT { --><p class=\"se-text-paragraph se-text-paragraph-align- \" style=\"\" id=\"SE-46a7b0ad-71c7-41db-8173-f61c5a0cd042\"><span style=\"color:#000000;\" class=\"se-fs- se-ff-  se-style-unset \" id=\"SE-d7419383-207e-403e-b1d6-e4d854362c3c\">​</span></p><!-- } SE-TEXT --><!-- SE-TEXT { --><p class=\"se-text-paragraph se-text-paragraph-align- \" style=\"\" id=\"SE-e1d94d4f-ab03-4740-942d-d5d0386e6ba1\"><span style=\"color:#000000;\" class=\"se-fs- se-ff-  se-style-unset \" id=\"SE-c9a4eda2-63f9-430f-9048-e413ba27d96e\">​</span></p><!-- } SE-TEXT --><!-- SE-TEXT { --><p class=\"se-text-paragraph se-text-paragraph-align- \" style=\"\" id=\"SE-afe1eee2-66d6-47ac-ab08-22fc7aa562aa\"><span style=\"color:#000000;\" class=\"se-fs- se-ff-  se-style-unset \" id=\"SE-fd9086e7-7443-4279-a3ef-3316084679f6\">​</span></p><!-- } SE-TEXT --><!-- SE-TEXT { --><p class=\"se-text-paragraph se-text-paragraph-align- \" style=\"\" id=\"SE-e3a50497-8d2c-4c05-85d6-1d3cec37fa21\"><span style=\"color:#000000;background-color:#ffffff;\" class=\"se-fs- se-ff-  se-style-unset \" id=\"SE-6822ee0a-2932-4c73-91c6-35921adefb39\"><span class=\"__se-hash-tag\">#구안와사한의원</span> <span class=\"__se-hash-tag\">#안면마비한의원</span> <span class=\"__se-hash-tag\">#안면신경마비한의원</span> <span class=\"__se-hash-tag\">#남성역한의원</span> <span class=\"__se-hash-tag\">#야간진료한의원</span> <span class=\"__se-hash-tag\">#일요일진료한의원</span> <span class=\"__se-hash-tag\">#야간진료</span> <span class=\"__se-hash-tag\">#일요일진료</span> <span class=\"__se-hash-tag\">#추나요법</span> <span class=\"__se-hash-tag\">#추나요법한의원</span> <span class=\"__se-hash-tag\">#남성역추나요법</span></span></p><!-- } SE-TEXT -->\n                            </div>\n                        </div>\n                    </div>\n                </div>    </div>",
  "meta": {
    "ogTitle": "구안와사(안면신경마비) 원인과 치료",
    "ogDesc": "한의학에서는 중풍(中風 - 뇌졸중)을 그 심한 정도에 따라 여러가지 단계로 나눕니다. 구안와사는 그 중에...",
    "ogImage": "https://blogthumb.pstatic.net/MjAyMDA4MTlfMjU5/MDAxNTk3ODA4ODA1Njgx.nPCU7ax6qcUlJvyIEkxuR18nl3iCcbmQK1t08m-hc74g.40eYMyzmAh2xGrakn80ZNPk3hcozw5faFgMClX0BMEog.PNG.isuhani/image.png?type=w2",
    "date": "2020. 8. 19. 12:50",
    "category": null
  },
  "images": [
    "https://www.ebmconsult.com/app/article/images/100030",
    "https://www.daviddarling.info/images/Bells_palsy.gif",
    "https://www.researchgate.net/profile/Carla_Baan/publication/336214881/figure/fig2/AS:872237502582785@1584969034212/Schematic-drawing-of-Wallerian-degeneration-following-peripheral-nerve-injury-a.png",
    "https://postfiles.pstatic.net/MjAyMDA4MTlfMjU5/MDAxNTk3ODA4ODA1Njgx.nPCU7ax6qcUlJvyIEkxuR18nl3iCcbmQK1t08m-hc74g.40eYMyzmAh2xGrakn80ZNPk3hcozw5faFgMClX0BMEog.PNG.isuhani/image.png?type=w580",
    "https://postfiles.pstatic.net/MjAyMDA4MTlfMTQ2/MDAxNTk3ODA4OTE3Mzcw.rxmZCN-aycZgvl1rFvVVMfcXYVKRXw8boZM48a46Blgg.xjwTvWgkeCq5JLOAaRIowwGWhoLcu9iLXigxatM_rfsg.PNG.isuhani/남성역_이수한의원.png?type=w580"
  ]
}