{
  "logNo": "222585182696",
  "blog": "metroparis",
  "title": "20대 허리디스크 일자목 전성시대",
  "addDate": "2021. 12. 2.",
  "categoryNo": "",
  "parentCategoryNo": "",
  "url": "https://blog.naver.com/PostView.naver?blogId=metroparis&logNo=222585182696",
  "blocks": [],
  "body": "<div class=\"se-main-container\">\n                <div class=\"se-component se-image se-l-default\" id=\"SE-9a81faa8-4f47-4588-addf-37a871fa0b7f\">\n                    <div class=\"se-component-content se-component-content-fit\">\n                        <div class=\"se-section se-section-image se-l-default se-section-align-center\" >\n                                <div class=\"se-module se-module-image\" style=\"\">\n                                    <a href=\"#\" class=\"se-module-image-link __se_image_link __se_link\" style=\"\" onclick=\"return false;\" data-linktype=\"img\" data-linkdata='{\"id\" : \"SE-9a81faa8-4f47-4588-addf-37a871fa0b7f\", \"src\" : \"https://isuhani-clinic-data.s3.ap-northeast-2.amazonaws.com/images/legacy/e3a736e8df22f0b4.png\", \"originalWidth\" : \"1080\", \"originalHeight\" : \"1080\", \"linkUse\" : \"false\", \"link\" : \"\"}'>\n                                        <img src=\"https://isuhani-clinic-data.s3.ap-northeast-2.amazonaws.com/images/legacy/e3a736e8df22f0b4.png\" data-lazy-src=\"https://isuhani-clinic-data.s3.ap-northeast-2.amazonaws.com/images/legacy/e3a736e8df22f0b4.png\" data-width=\"500\" data-height=\"500\" alt=\"\" class=\"se-image-resource\" />\n                                    </a>\n                                </div>\n                        </div>\n                    </div>\n                </div>\n                <div class=\"se-component se-text se-l-default\" id=\"SE-fc6b725f-bc94-407f-87e1-5e10c7450131\">\n                    <div class=\"se-component-content\">\n                        <div class=\"se-section se-section-text se-l-default\">\n                            <div class=\"se-module se-module-text\">\n                                    <!-- SE-TEXT { --><p class=\"se-text-paragraph se-text-paragraph-align-center \" style=\"\" id=\"SE-e8908557-f63e-4501-a28c-6bd7600de247\"><span style=\"\" class=\"se-fs- se-ff-   \" id=\"SE-91b95a35-64dd-465e-ac71-3417444999b9\">통증과 체형을 한번에!</span></p><!-- } SE-TEXT --><!-- SE-TEXT { --><p class=\"se-text-paragraph se-text-paragraph-align-center \" style=\"\" id=\"SE-0b02c886-b63d-4b8a-8647-ece6570f4be2\"><span style=\"\" class=\"se-fs- se-ff-   \" id=\"SE-c2578316-3a50-4725-9088-119978609f3f\">몸과 마음의 균형!</span></p><!-- } SE-TEXT --><!-- SE-TEXT { --><p class=\"se-text-paragraph se-text-paragraph-align-center \" style=\"\" id=\"SE-408042a4-8d5d-4fcf-991a-a47291e56fae\"><span style=\"\" class=\"se-fs- se-ff-   \" id=\"SE-90e6d883-5577-4911-bea2-7e696a9f45c3\">안녕하세요, 이수한의원입니다.</span></p><!-- } SE-TEXT --><!-- SE-TEXT { --><p class=\"se-text-paragraph se-text-paragraph-align-center \" style=\"\" id=\"SE-6374e29d-1bbe-43a4-82ca-a6456691b0a9\"><span style=\"\" class=\"se-fs- se-ff-   \" id=\"SE-c1796d92-6b27-4a31-9edc-241abcdfcc0b\">​</span></p><!-- } SE-TEXT --><!-- SE-TEXT { --><p class=\"se-text-paragraph se-text-paragraph-align-center \" style=\"\" id=\"SE-c842c2f4-4e16-4633-89a4-ece40a7f97b6\"><span style=\"\" class=\"se-fs- se-ff-   \" id=\"SE-e5368698-dabd-47dc-a2b2-879d8427fc18\">오늘은 통증해결 한방토크 첫 번째 시간,</span></p><!-- } SE-TEXT --><!-- SE-TEXT { --><p class=\"se-text-paragraph se-text-paragraph-align-center \" style=\"\" id=\"SE-620c3ffa-134c-446b-b94c-1aede01fcddb\"><span style=\"background-color:#fff8b2;\" class=\"se-fs- se-ff-   \" id=\"SE-0d12eb4f-0980-4d61-b116-5ef51c1018b3\"><b>&#x27;20대 허리디스크 일자목 전성시대&#x27;</b></span><span style=\"\" class=\"se-fs- se-ff-   \" id=\"SE-3393d52f-7ae6-409f-91ac-2eab36917d1e\">에 대한 이야기를 하려고 합니다</span></p><!-- } SE-TEXT --><!-- SE-TEXT { --><p class=\"se-text-paragraph se-text-paragraph-align-center \" style=\"\" id=\"SE-2e090a2c-e273-4a9d-80be-38d271a64d56\"><span style=\"\" class=\"se-fs- se-ff-   \" id=\"SE-bb215d38-b8b9-4d47-92e4-230e5d70138c\">평소 허리디스크나 일자목 등에 관심이 있으셨다면,</span></p><!-- } SE-TEXT --><!-- SE-TEXT { --><p class=\"se-text-paragraph se-text-paragraph-align-center \" style=\"\" id=\"SE-327cfa76-6f2b-440e-855c-b204577febfc\"><span style=\"\" class=\"se-fs- se-ff-   \" id=\"SE-273f21ef-3751-42e1-870a-fe13b9f99e2b\">오늘 콘텐츠를 주의깊게 읽어봐주세요!</span></p><!-- } SE-TEXT --><!-- SE-TEXT { --><p class=\"se-text-paragraph se-text-paragraph-align-center \" style=\"\" id=\"SE-e21c97de-32ce-4802-b7db-eaa9a65b509a\"><span style=\"\" class=\"se-fs- se-ff-   \" id=\"SE-5fd2924e-6d2e-4897-946f-d49e0b645f0d\">​</span></p><!-- } SE-TEXT -->\n                            </div>\n                        </div>\n                    </div>\n                </div>                <div class=\"se-component se-horizontalLine se-l-default\" id=\"SE-252ff19c-6034-41e7-8732-ae26712b04b6\">\n                    <div class=\"se-component-content\">\n                        <div class=\"se-section se-section-horizontalLine se-l-default se-section-align-center\">\n                            <div class=\"se-module se-module-horizontalLine\">\n                                <hr class=\"se-hr\" />\n                            </div>\n                        </div>\n                    </div>\n                </div>                <div class=\"se-component se-image se-l-default\" id=\"SE-ec40c641-320c-4995-bcad-9648923635dd\">\n                    <div class=\"se-component-content se-component-content-fit\">\n                        <div class=\"se-section se-section-image se-l-default se-section-align-center\" >\n                                <div class=\"se-module se-module-image\" style=\"\">\n                                    <a href=\"#\" class=\"se-module-image-link __se_image_link __se_link\" style=\"\" onclick=\"return false;\" data-linktype=\"img\" data-linkdata='{\"id\" : \"SE-ec40c641-320c-4995-bcad-9648923635dd\", \"src\" : \"https://isuhani-clinic-data.s3.ap-northeast-2.amazonaws.com/images/legacy/d6325549376bb399.png\", \"originalWidth\" : \"1080\", \"originalHeight\" : \"1080\", \"linkUse\" : \"false\", \"link\" : \"\"}'>\n                                        <img src=\"https://isuhani-clinic-data.s3.ap-northeast-2.amazonaws.com/images/legacy/d6325549376bb399.png\" data-lazy-src=\"https://isuhani-clinic-data.s3.ap-northeast-2.amazonaws.com/images/legacy/d6325549376bb399.png\" data-width=\"500\" data-height=\"500\" alt=\"\" class=\"se-image-resource\" />\n                                    </a>\n                                </div>\n                        </div>\n                    </div>\n                </div>\n                <div class=\"se-component se-text se-l-default\" id=\"SE-bc299a2b-6a16-49d6-b7f2-35ee0983d405\">\n                    <div class=\"se-component-content\">\n                        <div class=\"se-section se-section-text se-l-default\">\n                            <div class=\"se-module se-module-text\">\n                                    <!-- SE-TEXT { --><p class=\"se-text-paragraph se-text-paragraph-align-center \" style=\"\" id=\"SE-355a3edc-8035-481c-ac8c-5777a41a1e0f\"><span style=\"\" class=\"se-fs- se-ff-   \" id=\"SE-a35f8093-84f1-4c1a-9f09-253ba5b65472\">​</span></p><!-- } SE-TEXT --><!-- SE-TEXT { --><p class=\"se-text-paragraph se-text-paragraph-align-center \" style=\"\" id=\"SE-4a60b6fb-cf0f-47f6-a9c6-4d8ce4f33f42\"><span style=\"\" class=\"se-fs- se-ff-   \" id=\"SE-e5541e97-c01e-47c8-b0f5-2cf1640b10ea\">&quot;못도 씹어 먹겠네&quot;</span></p><!-- } SE-TEXT --><!-- SE-TEXT { --><p class=\"se-text-paragraph se-text-paragraph-align-center \" style=\"\" id=\"SE-347d5557-f0c5-4df6-9856-5b01b8668bdf\"><span style=\"\" class=\"se-fs- se-ff-   \" id=\"SE-21073f26-24c9-4c9c-aa74-3eace1f37e9e\">&quot;소도 때려잡겠다~&quot;</span></p><!-- } SE-TEXT --><!-- SE-TEXT { --><p class=\"se-text-paragraph se-text-paragraph-align-center \" style=\"\" id=\"SE-989b10e5-bd5d-42c6-81d7-3215a78374b8\"><span style=\"\" class=\"se-fs- se-ff-   \" id=\"SE-020954a1-2027-4a3c-beab-f17e076bbb8c\">20대라고 하면 평소에 자주 듣는 말들인데요,</span></p><!-- } SE-TEXT --><!-- SE-TEXT { --><p class=\"se-text-paragraph se-text-paragraph-align-center \" style=\"\" id=\"SE-c6f1147d-806c-429f-b56a-b9f48c276431\"><span style=\"\" class=\"se-fs- se-ff-   \" id=\"SE-5c431cfc-6feb-4dce-87fb-a3a86f4856f6\">20대 특유의 젊음, 활기차고 팔팔한 모습들.</span></p><!-- } SE-TEXT --><!-- SE-TEXT { --><p class=\"se-text-paragraph se-text-paragraph-align-center \" style=\"\" id=\"SE-964a03e5-6053-4292-bf15-cbde7e1ee2d1\"><span style=\"\" class=\"se-fs- se-ff-   \" id=\"SE-ccfa71c8-20a0-4263-aa75-222933871571\">​</span></p><!-- } SE-TEXT --><!-- SE-TEXT { --><p class=\"se-text-paragraph se-text-paragraph-align-center \" style=\"\" id=\"SE-15b5cba4-f36d-4e13-a583-92c91ba033c6\"><span style=\"\" class=\"se-fs- se-ff-   \" id=\"SE-8328999c-f342-4105-8e97-d816c90cad01\">그런데 과연 20대들의 현실과 맞는 이야기일까요?</span></p><!-- } SE-TEXT --><!-- SE-TEXT { --><p class=\"se-text-paragraph se-text-paragraph-align-center \" style=\"\" id=\"SE-a59a42e8-7af2-4779-9e0e-f22d352752b8\"><span style=\"\" class=\"se-fs- se-ff-   \" id=\"SE-00c165ab-e6ff-497a-a018-8fc788867b06\">​</span></p><!-- } SE-TEXT --><!-- SE-TEXT { --><p class=\"se-text-paragraph se-text-paragraph-align-center \" style=\"\" id=\"SE-6afd3c5a-eb36-4472-b5d9-ee4e3cae0586\"><span style=\"\" class=\"se-fs- se-ff-   \" id=\"SE-bf90aeeb-c9cc-4c28-a249-60a52384e55e\">​</span></p><!-- } SE-TEXT -->\n                            </div>\n                        </div>\n                    </div>\n                </div>                <div class=\"se-component se-image se-l-default\" id=\"SE-01f2df0c-205b-4daf-9bd8-876d077c8fd8\">\n                    <div class=\"se-component-content se-component-content-fit\">\n                        <div class=\"se-section se-section-image se-l-default se-section-align-center\" >\n                                <div class=\"se-module se-module-image\" style=\"\">\n                                    <a href=\"#\" class=\"se-module-image-link __se_image_link __se_link\" style=\"\" onclick=\"return false;\" data-linktype=\"img\" data-linkdata='{\"id\" : \"SE-01f2df0c-205b-4daf-9bd8-876d077c8fd8\", \"src\" : \"https://isuhani-clinic-data.s3.ap-northeast-2.amazonaws.com/images/legacy/c147a1acd7415621.png\", \"originalWidth\" : \"1080\", \"originalHeight\" : \"1080\", \"linkUse\" : \"false\", \"link\" : \"\"}'>\n                                        <img src=\"https://isuhani-clinic-data.s3.ap-northeast-2.amazonaws.com/images/legacy/c147a1acd7415621.png\" data-lazy-src=\"https://isuhani-clinic-data.s3.ap-northeast-2.amazonaws.com/images/legacy/c147a1acd7415621.png\" data-width=\"500\" data-height=\"500\" alt=\"\" class=\"se-image-resource\" />\n                                    </a>\n                                </div>\n                        </div>\n                    </div>\n                </div>\n                <div class=\"se-component se-text se-l-default\" id=\"SE-8e1594c2-e889-4d21-8941-142ebe10b4fb\">\n                    <div class=\"se-component-content\">\n                        <div class=\"se-section se-section-text se-l-default\">\n                            <div class=\"se-module se-module-text\">\n                                    <!-- SE-TEXT { --><p class=\"se-text-paragraph se-text-paragraph-align-center \" style=\"\" id=\"SE-a75be87e-2a60-410c-be7c-b4eec88d2ab7\"><span style=\"\" class=\"se-fs- se-ff-   \" id=\"SE-1e4f89e3-ee94-41d0-94e4-e766388d046b\">​</span></p><!-- } SE-TEXT --><!-- SE-TEXT { --><p class=\"se-text-paragraph se-text-paragraph-align-center \" style=\"\" id=\"SE-d1a018cc-4dfb-4749-9f68-b78fc4531d76\"><span style=\"\" class=\"se-fs- se-ff-   \" id=\"SE-ea8e02e3-a9eb-444b-aeda-c57dc03977af\">요즘 20대들은 </span><span style=\"background-color:#fff8b2;\" class=\"se-fs- se-ff-   \" id=\"SE-d4d3fa34-7612-4ab5-aa79-7e26338f7850\"><b>&#x27;일자목&#x27;</b></span><span style=\"\" class=\"se-fs- se-ff-   \" id=\"SE-5fcedeb7-b7b8-4248-a235-e05c7034735d\">으로 고통받고 있다고 합니다.</span></p><!-- } SE-TEXT --><!-- SE-TEXT { --><p class=\"se-text-paragraph se-text-paragraph-align-center \" style=\"\" id=\"SE-3f8227bf-2f47-4f4d-b1f5-b096d4fe9a58\"><span style=\"\" class=\"se-fs- se-ff-   \" id=\"SE-b908000d-a81d-439b-b205-190c59f403d4\">목뼈 변형, 목 디스크 등</span></p><!-- } SE-TEXT --><!-- SE-TEXT { --><p class=\"se-text-paragraph se-text-paragraph-align-center \" style=\"\" id=\"SE-fa041894-26fa-45da-8214-aff5b3cf7198\"><span style=\"\" class=\"se-fs- se-ff-   \" id=\"SE-0a4b7dc8-4db7-4bfb-a3b9-1cd4801beb93\">목과 관련된 통증이 이어지면서</span></p><!-- } SE-TEXT --><!-- SE-TEXT { --><p class=\"se-text-paragraph se-text-paragraph-align-center \" style=\"\" id=\"SE-0c051641-ac98-4a86-b5c8-624d525cefd1\"><span style=\"\" class=\"se-fs- se-ff-   \" id=\"SE-a0f3bf76-6adf-4cd1-8fd1-405caed21f14\">이에 대한 아픔을 호소하고 있는 것인데요,</span></p><!-- } SE-TEXT --><!-- SE-TEXT { --><p class=\"se-text-paragraph se-text-paragraph-align-center \" style=\"\" id=\"SE-e4558f0c-2557-4b98-8c69-0bd9f6ac8e0a\"><span style=\"\" class=\"se-fs- se-ff-   \" id=\"SE-169a63c3-7260-4516-bc72-8618ce831b90\">​</span></p><!-- } SE-TEXT --><!-- SE-TEXT { --><p class=\"se-text-paragraph se-text-paragraph-align-center \" style=\"\" id=\"SE-fe805360-26a4-4438-9dd6-fdb829c86786\"><span style=\"\" class=\"se-fs- se-ff-   \" id=\"SE-c8cf3bb1-4d5e-4717-80bc-22930d4d816d\">​</span></p><!-- } SE-TEXT -->\n                            </div>\n                        </div>\n                    </div>\n                </div>                <div class=\"se-component se-image se-l-default\" id=\"SE-e851bd76-72da-44f4-96fe-0e9c050be726\">\n                    <div class=\"se-component-content se-component-content-fit\">\n                        <div class=\"se-section se-section-image se-l-default se-section-align-center\" >\n                                <div class=\"se-module se-module-image\" style=\"\">\n                                    <a href=\"#\" class=\"se-module-image-link __se_image_link __se_link\" style=\"\" onclick=\"return false;\" data-linktype=\"img\" data-linkdata='{\"id\" : \"SE-e851bd76-72da-44f4-96fe-0e9c050be726\", \"src\" : \"https://isuhani-clinic-data.s3.ap-northeast-2.amazonaws.com/images/legacy/030e006f9a4a6668.png\", \"originalWidth\" : \"1080\", \"originalHeight\" : \"1080\", \"linkUse\" : \"false\", \"link\" : \"\"}'>\n                                        <img src=\"https://isuhani-clinic-data.s3.ap-northeast-2.amazonaws.com/images/legacy/030e006f9a4a6668.png\" data-lazy-src=\"https://isuhani-clinic-data.s3.ap-northeast-2.amazonaws.com/images/legacy/030e006f9a4a6668.png\" data-width=\"500\" data-height=\"500\" alt=\"\" class=\"se-image-resource\" />\n                                    </a>\n                                </div>\n                        </div>\n                    </div>\n                </div>\n                <div class=\"se-component se-text se-l-default\" id=\"SE-ace9e466-7a00-44ce-8325-ab2ef9675a03\">\n                    <div class=\"se-component-content\">\n                        <div class=\"se-section se-section-text se-l-default\">\n                            <div class=\"se-module se-module-text\">\n                                    <!-- SE-TEXT { --><p class=\"se-text-paragraph se-text-paragraph-align-center \" style=\"\" id=\"SE-d1d3ea63-d1c2-4313-90dd-5f15c3ea6d7b\"><span style=\"\" class=\"se-fs- se-ff-   \" id=\"SE-4f2d67c8-c836-48c3-a958-8cae7b3f5478\">​</span></p><!-- } SE-TEXT --><!-- SE-TEXT { --><p class=\"se-text-paragraph se-text-paragraph-align-center \" style=\"\" id=\"SE-1c7a4a53-401f-4ab5-a06e-efb2a51fc6f3\"><span style=\"\" class=\"se-fs- se-ff-   \" id=\"SE-623b10f4-4369-4b2e-9f92-368131ad0564\">이러한 통증은</span></p><!-- } SE-TEXT --><!-- SE-TEXT { --><p class=\"se-text-paragraph se-text-paragraph-align-center \" style=\"\" id=\"SE-8fe5208b-1859-4e3a-92f0-02907c0f3b23\"><span style=\"\" class=\"se-fs- se-ff-   \" id=\"SE-21d51333-14e8-4276-b46b-139c15094b90\">잘못된 식습관, 과로,</span></p><!-- } SE-TEXT --><!-- SE-TEXT { --><p class=\"se-text-paragraph se-text-paragraph-align-center \" style=\"\" id=\"SE-d183532c-1bed-4c05-8ba7-986db3ed11f7\"><span style=\"\" class=\"se-fs- se-ff-   \" id=\"SE-fe00d3eb-5937-40ea-99ee-2c9cbfcc2ef1\">스트레스, 운동 부족 등</span></p><!-- } SE-TEXT --><!-- SE-TEXT { --><p class=\"se-text-paragraph se-text-paragraph-align-center \" style=\"\" id=\"SE-c53c4658-e788-426e-ac19-8a4ef23e6b3d\"><span style=\"\" class=\"se-fs- se-ff-   \" id=\"SE-35cc4ea6-b8df-4461-bf47-43e10e09e41b\">다양한 원인으로 인해 생겨납니다.</span></p><!-- } SE-TEXT --><!-- SE-TEXT { --><p class=\"se-text-paragraph se-text-paragraph-align-center \" style=\"\" id=\"SE-e51fae71-c03d-4f63-93ab-31294ad5ac65\"><span style=\"\" class=\"se-fs- se-ff-   \" id=\"SE-9c246b3f-7de1-409a-9cfb-36b81ecfea09\">​</span></p><!-- } SE-TEXT --><!-- SE-TEXT { --><p class=\"se-text-paragraph se-text-paragraph-align-center \" style=\"\" id=\"SE-9a8f36ed-aef8-4498-b0d3-5b6e1014cdef\"><span style=\"\" class=\"se-fs- se-ff-   \" id=\"SE-b87c3401-4b62-44d8-9723-df7f4a47e133\">​</span></p><!-- } SE-TEXT -->\n                            </div>\n                        </div>\n                    </div>\n                </div>                <div class=\"se-component se-image se-l-default\" id=\"SE-27ba473c-61be-4617-abac-b75c61724983\">\n                    <div class=\"se-component-content se-component-content-fit\">\n                        <div class=\"se-section se-section-image se-l-default se-section-align-center\" >\n                                <div class=\"se-module se-module-image\" style=\"\">\n                                    <a href=\"#\" class=\"se-module-image-link __se_image_link __se_link\" style=\"\" onclick=\"return false;\" data-linktype=\"img\" data-linkdata='{\"id\" : \"SE-27ba473c-61be-4617-abac-b75c61724983\", \"src\" : \"https://isuhani-clinic-data.s3.ap-northeast-2.amazonaws.com/images/legacy/42842e8d70644435.png\", \"originalWidth\" : \"1080\", \"originalHeight\" : \"1080\", \"linkUse\" : \"false\", \"link\" : \"\"}'>\n                                        <img src=\"https://isuhani-clinic-data.s3.ap-northeast-2.amazonaws.com/images/legacy/42842e8d70644435.png\" data-lazy-src=\"https://isuhani-clinic-data.s3.ap-northeast-2.amazonaws.com/images/legacy/42842e8d70644435.png\" data-width=\"500\" data-height=\"500\" alt=\"\" class=\"se-image-resource\" />\n                                    </a>\n                                </div>\n                        </div>\n                    </div>\n                </div>\n                <div class=\"se-component se-text se-l-default\" id=\"SE-c843d855-3f87-4748-bfb2-568742ea286d\">\n                    <div class=\"se-component-content\">\n                        <div class=\"se-section se-section-text se-l-default\">\n                            <div class=\"se-module se-module-text\">\n                                    <!-- SE-TEXT { --><p class=\"se-text-paragraph se-text-paragraph-align-center \" style=\"\" id=\"SE-7007bf0a-e602-4ff5-82ef-a1c86d21486f\"><span style=\"\" class=\"se-fs- se-ff-   \" id=\"SE-f7e98b8e-3dcc-4f79-8c27-ca9344ccc8fd\">​</span></p><!-- } SE-TEXT --><!-- SE-TEXT { --><p class=\"se-text-paragraph se-text-paragraph-align-center \" style=\"\" id=\"SE-3e07592f-65c2-4208-9dfa-a6334d46d3c7\"><span style=\"\" class=\"se-fs- se-ff-   \" id=\"SE-0442d23d-d3cb-49d3-938b-0fd2aab6f021\">그러나 그 중에서도 가장 큰 원인은</span></p><!-- } SE-TEXT --><!-- SE-TEXT { --><p class=\"se-text-paragraph se-text-paragraph-align-center \" style=\"\" id=\"SE-d0c335d1-0cee-4f5b-849f-89f9e3f6f4e2\"><span style=\"\" class=\"se-fs- se-ff-   \" id=\"SE-f6e401e7-30f1-4b9b-ab34-2eafb59b8f34\">바로 </span><span style=\"\" class=\"se-fs- se-ff-   \" id=\"SE-f4f5e461-6c69-40bc-addc-564b7068719c\"><b>잘못된 생활 습관</b></span><span style=\"\" class=\"se-fs- se-ff-   \" id=\"SE-caa9decc-98bb-4146-a025-abe23deab45e\">!</span></p><!-- } SE-TEXT --><!-- SE-TEXT { --><p class=\"se-text-paragraph se-text-paragraph-align-center \" style=\"\" id=\"SE-310d7cff-f9af-4620-8c0b-10430c57f22b\"><span style=\"\" class=\"se-fs- se-ff-   \" id=\"SE-8deb776c-26e6-4da1-9512-cd939b9c1ae2\">​</span></p><!-- } SE-TEXT --><!-- SE-TEXT { --><p class=\"se-text-paragraph se-text-paragraph-align-center \" style=\"\" id=\"SE-56e12db0-3067-4a28-9578-a43af8ab444c\"><span style=\"\" class=\"se-fs- se-ff-   \" id=\"SE-25023393-214d-4f46-8a87-e81463d7b6c3\">​</span></p><!-- } SE-TEXT -->\n                            </div>\n                        </div>\n                    </div>\n                </div>                <div class=\"se-component se-image se-l-default\" id=\"SE-11a383fd-e1c0-4b2f-817b-30670e30763a\">\n                    <div class=\"se-component-content se-component-content-fit\">\n                        <div class=\"se-section se-section-image se-l-default se-section-align-center\" >\n                                <div class=\"se-module se-module-image\" style=\"\">\n                                    <a href=\"#\" class=\"se-module-image-link __se_image_link __se_link\" style=\"\" onclick=\"return false;\" data-linktype=\"img\" data-linkdata='{\"id\" : \"SE-11a383fd-e1c0-4b2f-817b-30670e30763a\", \"src\" : \"https://isuhani-clinic-data.s3.ap-northeast-2.amazonaws.com/images/legacy/b5f4853be314d8da.png\", \"originalWidth\" : \"1080\", \"originalHeight\" : \"1080\", \"linkUse\" : \"false\", \"link\" : \"\"}'>\n                                        <img src=\"https://isuhani-clinic-data.s3.ap-northeast-2.amazonaws.com/images/legacy/b5f4853be314d8da.png\" data-lazy-src=\"https://isuhani-clinic-data.s3.ap-northeast-2.amazonaws.com/images/legacy/b5f4853be314d8da.png\" data-width=\"500\" data-height=\"500\" alt=\"\" class=\"se-image-resource\" />\n                                    </a>\n                                </div>\n                        </div>\n                    </div>\n                </div>\n                <div class=\"se-component se-text se-l-default\" id=\"SE-31f018a2-8a13-44d9-846a-ca9f8248d1b3\">\n                    <div class=\"se-component-content\">\n                        <div class=\"se-section se-section-text se-l-default\">\n                            <div class=\"se-module se-module-text\">\n                                    <!-- SE-TEXT { --><p class=\"se-text-paragraph se-text-paragraph-align-center \" style=\"\" id=\"SE-e020f4b0-6941-470e-9f58-f148f7120b0d\"><span style=\"\" class=\"se-fs- se-ff-   \" id=\"SE-0c97fcd2-e584-4378-9035-d8c362f6fce9\">​</span></p><!-- } SE-TEXT --><!-- SE-TEXT { --><p class=\"se-text-paragraph se-text-paragraph-align-center \" style=\"\" id=\"SE-64246d25-b7dd-4148-a707-0ce88450d2f4\"><span style=\"\" class=\"se-fs- se-ff-   \" id=\"SE-bc1ff26b-5e6f-4bc5-96ae-09cba656c9b9\">혹시 위의 사진이 평소 모습과 비슷하신가요?</span></p><!-- } SE-TEXT --><!-- SE-TEXT { --><p class=\"se-text-paragraph se-text-paragraph-align-center \" style=\"\" id=\"SE-5fc6d916-b422-407a-a825-158eea63d428\"><span style=\"\" class=\"se-fs- se-ff-   \" id=\"SE-41e6ec3d-e4c4-4e35-a078-e0423c615e76\">사진에 있는 자세들은 모두</span></p><!-- } SE-TEXT --><!-- SE-TEXT { --><p class=\"se-text-paragraph se-text-paragraph-align-center \" style=\"\" id=\"SE-fe00036d-7be1-455d-856f-a845b46556a8\"><span style=\"\" class=\"se-fs- se-ff-   \" id=\"SE-4480e866-0e4c-40bc-bf37-5135016b6ca1\">일자목을 부르는 잘못된 습관들!</span></p><!-- } SE-TEXT --><!-- SE-TEXT { --><p class=\"se-text-paragraph se-text-paragraph-align-center \" style=\"\" id=\"SE-90865039-aed0-49f9-ab97-1221e68cb0b5\"><span style=\"\" class=\"se-fs- se-ff-   \" id=\"SE-5e272318-19b1-4fe3-82c5-c4431d220338\">​</span></p><!-- } SE-TEXT --><!-- SE-TEXT { --><p class=\"se-text-paragraph se-text-paragraph-align-center \" style=\"\" id=\"SE-65428de8-581a-4a5a-a549-8e0ce935aeae\"><span style=\"\" class=\"se-fs- se-ff-   \" id=\"SE-562630bd-28c8-483c-a29c-301dd068fd0e\">이러한 잘못된 습관들이 모여서</span></p><!-- } SE-TEXT --><!-- SE-TEXT { --><p class=\"se-text-paragraph se-text-paragraph-align-center \" style=\"\" id=\"SE-47d31f7f-2eb4-4244-9272-2b3e60801eba\"><span style=\"\" class=\"se-fs- se-ff-   \" id=\"SE-9e62a055-2ee8-4c2c-9a6c-3fcf57619607\">목 통증을 불러오고,</span></p><!-- } SE-TEXT --><!-- SE-TEXT { --><p class=\"se-text-paragraph se-text-paragraph-align-center \" style=\"\" id=\"SE-79178981-168a-4ae9-add8-9cb24041e7f2\"><span style=\"\" class=\"se-fs- se-ff-   \" id=\"SE-0b77e3ae-ba2e-4739-a50b-d93c7beddc7d\">이어서 일자목, 목 디스크들을 유발하게 됩니다.</span></p><!-- } SE-TEXT --><!-- SE-TEXT { --><p class=\"se-text-paragraph se-text-paragraph-align-center \" style=\"\" id=\"SE-4312c185-8240-4df3-b9e7-26b7b80c711a\"><span style=\"\" class=\"se-fs- se-ff-   \" id=\"SE-82ce0e29-eeb6-4a03-95fd-c0f76ec4b192\">​</span></p><!-- } SE-TEXT --><!-- SE-TEXT { --><p class=\"se-text-paragraph se-text-paragraph-align-center \" style=\"\" id=\"SE-23535bc7-6874-48b5-9481-2262fb273d48\"><span style=\"\" class=\"se-fs- se-ff-   \" id=\"SE-a4cdbe00-a6f3-4f08-840a-928dbd34681f\">​</span></p><!-- } SE-TEXT -->\n                            </div>\n                        </div>\n                    </div>\n                </div>                <div class=\"se-component se-image se-l-default\" id=\"SE-2e18e6e7-b603-4bfd-8a88-b4df771539f8\">\n                    <div class=\"se-component-content se-component-content-fit\">\n                        <div class=\"se-section se-section-image se-l-default se-section-align-center\" >\n                                <div class=\"se-module se-module-image\" style=\"\">\n                                    <a href=\"#\" class=\"se-module-image-link __se_image_link __se_link\" style=\"\" onclick=\"return false;\" data-linktype=\"img\" data-linkdata='{\"id\" : \"SE-2e18e6e7-b603-4bfd-8a88-b4df771539f8\", \"src\" : \"https://isuhani-clinic-data.s3.ap-northeast-2.amazonaws.com/images/legacy/685885ca3abd76e2.png\", \"originalWidth\" : \"1080\", \"originalHeight\" : \"1080\", \"linkUse\" : \"false\", \"link\" : \"\"}'>\n                                        <img src=\"https://isuhani-clinic-data.s3.ap-northeast-2.amazonaws.com/images/legacy/685885ca3abd76e2.png\" data-lazy-src=\"https://isuhani-clinic-data.s3.ap-northeast-2.amazonaws.com/images/legacy/685885ca3abd76e2.png\" data-width=\"500\" data-height=\"500\" alt=\"\" class=\"se-image-resource\" />\n                                    </a>\n                                </div>\n                        </div>\n                    </div>\n                </div>\n                <div class=\"se-component se-text se-l-default\" id=\"SE-2a57a77f-ac91-4041-a955-1c42062c4c4f\">\n                    <div class=\"se-component-content\">\n                        <div class=\"se-section se-section-text se-l-default\">\n                            <div class=\"se-module se-module-text\">\n                                    <!-- SE-TEXT { --><p class=\"se-text-paragraph se-text-paragraph-align-center \" style=\"\" id=\"SE-2b1c3dfd-d891-4247-90a4-77503c04984d\"><span style=\"\" class=\"se-fs- se-ff-   \" id=\"SE-520db6e9-b46d-4090-aeec-d6a7282d7c8a\">​</span></p><!-- } SE-TEXT --><!-- SE-TEXT { --><p class=\"se-text-paragraph se-text-paragraph-align-center \" style=\"\" id=\"SE-1d2d276b-d59a-4cba-9ac7-524411b623d5\"><span style=\"\" class=\"se-fs- se-ff-   \" id=\"SE-fa3e778b-7a54-4461-b85f-ffbfb0f9c34f\">그렇기에 평소에 의자에 앉아있을 때</span></p><!-- } SE-TEXT --><!-- SE-TEXT { --><p class=\"se-text-paragraph se-text-paragraph-align-center \" style=\"\" id=\"SE-f7d466dd-84d5-449f-8390-ecc968c381b3\"><span style=\"\" class=\"se-fs- se-ff-   \" id=\"SE-1a9478c1-2e8b-43c2-bf72-df0455433109\">올바른 자세를 유지하는 것이 매우 중요합니다!</span></p><!-- } SE-TEXT --><!-- SE-TEXT { --><p class=\"se-text-paragraph se-text-paragraph-align-center \" style=\"\" id=\"SE-017ea80d-0d37-497d-b865-7e08f4580e82\"><span style=\"\" class=\"se-fs- se-ff-   \" id=\"SE-437b2762-ace0-4d0c-87f4-d2cdaf0be84e\">​</span></p><!-- } SE-TEXT --><!-- SE-TEXT { --><p class=\"se-text-paragraph se-text-paragraph-align-center \" style=\"\" id=\"SE-377c8b5e-a61e-46a2-9bb8-df9e435dfdbe\"><span style=\"\" class=\"se-fs- se-ff-   \" id=\"SE-65ac8047-fef5-4ba6-b63a-8d173da46cb9\">그렇다면 일자목을 탈출하기 위핸</span></p><!-- } SE-TEXT --><!-- SE-TEXT { --><p class=\"se-text-paragraph se-text-paragraph-align-center \" style=\"\" id=\"SE-c28caf53-3b9e-485e-aa45-addecf8d4941\"><span style=\"\" class=\"se-fs- se-ff-   \" id=\"SE-bafa4cd5-1ac6-446a-ba0a-f64b0e71ee9b\">올바른 생활습관들에 대해 알아볼까요?</span></p><!-- } SE-TEXT --><!-- SE-TEXT { --><p class=\"se-text-paragraph se-text-paragraph-align-center \" style=\"\" id=\"SE-eb0c8ca2-4d1b-419a-b789-e8ec90af976c\"><span style=\"\" class=\"se-fs- se-ff-   \" id=\"SE-4cc48a7c-24cc-4cc9-a2c6-7203116febd9\">​</span></p><!-- } SE-TEXT --><!-- SE-TEXT { --><p class=\"se-text-paragraph se-text-paragraph-align-center \" style=\"\" id=\"SE-0ea178ad-581f-4345-88db-aeaf039a8ef2\"><span style=\"\" class=\"se-fs- se-ff-   \" id=\"SE-28e43739-23c4-4411-878d-7a1b02661f39\">​</span></p><!-- } SE-TEXT -->\n                            </div>\n                        </div>\n                    </div>\n                </div>                <div class=\"se-component se-image se-l-default\" id=\"SE-ba04a629-313e-4f89-9cef-86b05e4fc6ef\">\n                    <div class=\"se-component-content se-component-content-fit\">\n                        <div class=\"se-section se-section-image se-l-default se-section-align-center\" >\n                                <div class=\"se-module se-module-image\" style=\"\">\n                                    <a href=\"#\" class=\"se-module-image-link __se_image_link __se_link\" style=\"\" onclick=\"return false;\" data-linktype=\"img\" data-linkdata='{\"id\" : \"SE-ba04a629-313e-4f89-9cef-86b05e4fc6ef\", \"src\" : \"https://isuhani-clinic-data.s3.ap-northeast-2.amazonaws.com/images/legacy/5fccecb0fbec324a.png\", \"originalWidth\" : \"1080\", \"originalHeight\" : \"1080\", \"linkUse\" : \"false\", \"link\" : \"\"}'>\n                                        <img src=\"https://isuhani-clinic-data.s3.ap-northeast-2.amazonaws.com/images/legacy/5fccecb0fbec324a.png\" data-lazy-src=\"https://isuhani-clinic-data.s3.ap-northeast-2.amazonaws.com/images/legacy/5fccecb0fbec324a.png\" data-width=\"500\" data-height=\"500\" alt=\"\" class=\"se-image-resource\" />\n                                    </a>\n                                </div>\n                        </div>\n                    </div>\n                </div>\n                <div class=\"se-component se-text se-l-default\" id=\"SE-ac704ac0-f957-42f2-9040-05c64557b7a8\">\n                    <div class=\"se-component-content\">\n                        <div class=\"se-section se-section-text se-l-default\">\n                            <div class=\"se-module se-module-text\">\n                                    <!-- SE-TEXT { --><p class=\"se-text-paragraph se-text-paragraph-align-center \" style=\"\" id=\"SE-2cd0bd6f-ef3e-4a32-83a0-09479a217fbf\"><span style=\"\" class=\"se-fs- se-ff-   \" id=\"SE-50852525-efd9-4097-9c51-ef031156890c\">​</span></p><!-- } SE-TEXT --><!-- SE-TEXT { --><p class=\"se-text-paragraph se-text-paragraph-align-center \" style=\"\" id=\"SE-5e3877aa-990a-4820-8c77-460ed7cd858b\"><span style=\"background-color:#fff8b2;\" class=\"se-fs- se-ff-   \" id=\"SE-cd8888aa-8078-4adb-ab72-ba80a4302397\"><b>1. 회전 의자가 아닌 고정식 의자에 앉는다.</b></span></p><!-- } SE-TEXT --><!-- SE-TEXT { --><p class=\"se-text-paragraph se-text-paragraph-align-center \" style=\"\" id=\"SE-f7266fb8-aac0-4631-bd65-8156a46d48a8\"><span style=\"\" class=\"se-fs- se-ff-   \" id=\"SE-dddf6c0d-e0dc-4f32-b294-4ce0ea5bc14f\">​</span></p><!-- } SE-TEXT --><!-- SE-TEXT { --><p class=\"se-text-paragraph se-text-paragraph-align-center \" style=\"\" id=\"SE-a393b91c-de51-4f92-bf75-0fac7b5d112e\"><span style=\"\" class=\"se-fs- se-ff-   \" id=\"SE-99a85eac-d05e-42fc-9fd8-161eba3f74fa\">잘 미끄러지는 회전 의자는</span></p><!-- } SE-TEXT --><!-- SE-TEXT { --><p class=\"se-text-paragraph se-text-paragraph-align-center \" style=\"\" id=\"SE-87e18448-2306-4319-b6ec-9a524b12e834\"><span style=\"\" class=\"se-fs- se-ff-   \" id=\"SE-21a40793-607b-4c6a-a02c-3c592601a61f\">그만큼 나쁜 자세로 가기 쉽습니다.</span></p><!-- } SE-TEXT --><!-- SE-TEXT { --><p class=\"se-text-paragraph se-text-paragraph-align-center \" style=\"\" id=\"SE-1b454331-6cc9-44c7-b3eb-95332dd3e4af\"><span style=\"\" class=\"se-fs- se-ff-   \" id=\"SE-3428543f-8830-4f75-bd89-fd312e0c67d7\">고정된 의자에서 바른 자세를 계속해서 유지하는 것을 권장합니다!</span></p><!-- } SE-TEXT --><!-- SE-TEXT { --><p class=\"se-text-paragraph se-text-paragraph-align-center \" style=\"\" id=\"SE-7c804bdf-4148-46e3-9067-109d4609baf4\"><span style=\"\" class=\"se-fs- se-ff-   \" id=\"SE-924693b1-be33-40da-ba75-e608c1aacfe0\">​</span></p><!-- } SE-TEXT --><!-- SE-TEXT { --><p class=\"se-text-paragraph se-text-paragraph-align-center \" style=\"\" id=\"SE-a9c71adb-44a1-41bc-92e7-25da20eccb77\"><span style=\"\" class=\"se-fs- se-ff-   \" id=\"SE-f0ec271a-31e1-4e26-ab71-d35f417d4cb6\">​</span></p><!-- } SE-TEXT -->\n                            </div>\n                        </div>\n                    </div>\n                </div>                <div class=\"se-component se-image se-l-default\" id=\"SE-d3b1e19c-f57a-42de-bda3-393c2c057b4a\">\n                    <div class=\"se-component-content se-component-content-fit\">\n                        <div class=\"se-section se-section-image se-l-default se-section-align-center\" >\n                                <div class=\"se-module se-module-image\" style=\"\">\n                                    <a href=\"#\" class=\"se-module-image-link __se_image_link __se_link\" style=\"\" onclick=\"return false;\" data-linktype=\"img\" data-linkdata='{\"id\" : \"SE-d3b1e19c-f57a-42de-bda3-393c2c057b4a\", \"src\" : \"https://isuhani-clinic-data.s3.ap-northeast-2.amazonaws.com/images/legacy/bf8e71933c5f0ace.png\", \"originalWidth\" : \"1080\", \"originalHeight\" : \"1080\", \"linkUse\" : \"false\", \"link\" : \"\"}'>\n                                        <img src=\"https://isuhani-clinic-data.s3.ap-northeast-2.amazonaws.com/images/legacy/bf8e71933c5f0ace.png\" data-lazy-src=\"https://isuhani-clinic-data.s3.ap-northeast-2.amazonaws.com/images/legacy/bf8e71933c5f0ace.png\" data-width=\"500\" data-height=\"500\" alt=\"\" class=\"se-image-resource\" />\n                                    </a>\n                                </div>\n                        </div>\n                    </div>\n                </div>\n                <div class=\"se-component se-text se-l-default\" id=\"SE-5954ed05-c4fc-4ce5-a508-1a46aaf16a52\">\n                    <div class=\"se-component-content\">\n                        <div class=\"se-section se-section-text se-l-default\">\n                            <div class=\"se-module se-module-text\">\n                                    <!-- SE-TEXT { --><p class=\"se-text-paragraph se-text-paragraph-align-center \" style=\"\" id=\"SE-e2f28680-fc93-4c8a-9800-86bcd410e733\"><span style=\"\" class=\"se-fs- se-ff-   \" id=\"SE-8293d852-8562-477a-8ce6-35b62b691dfb\"><b>​</b></span></p><!-- } SE-TEXT --><!-- SE-TEXT { --><p class=\"se-text-paragraph se-text-paragraph-align-center \" style=\"\" id=\"SE-7a1e4ff7-c383-467f-9f79-aeb8d32be17e\"><span style=\"background-color:#fff8b2;\" class=\"se-fs- se-ff-   \" id=\"SE-ceaba0ad-d983-46d5-8cdf-6fe0cbb07611\"><b>2. 엉덩이는 등받이에 밀착한다.</b></span></p><!-- } SE-TEXT --><!-- SE-TEXT { --><p class=\"se-text-paragraph se-text-paragraph-align-center \" style=\"\" id=\"SE-234e026e-7172-4721-9b03-d62c57e5267d\"><span style=\"\" class=\"se-fs- se-ff-   \" id=\"SE-15f6799a-a5c8-4582-86ec-dc8f222bd750\">​</span></p><!-- } SE-TEXT --><!-- SE-TEXT { --><p class=\"se-text-paragraph se-text-paragraph-align-center \" style=\"\" id=\"SE-30424372-3bbb-40a4-b166-a048031e78d4\"><span style=\"\" class=\"se-fs- se-ff-   \" id=\"SE-142adbb5-e109-493e-b222-fd3e0c488607\">의자에 앉았을 때,</span></p><!-- } SE-TEXT --><!-- SE-TEXT { --><p class=\"se-text-paragraph se-text-paragraph-align-center \" style=\"\" id=\"SE-c7951de1-0b4f-4b7a-a25a-4d9662309563\"><span style=\"\" class=\"se-fs- se-ff-   \" id=\"SE-17c78d8c-7bbe-44fa-a33e-c8f91e973dec\">엉덩이는 의자 등받이에 밀착시키는 것이 좋습니다.</span></p><!-- } SE-TEXT --><!-- SE-TEXT { --><p class=\"se-text-paragraph se-text-paragraph-align-center \" style=\"\" id=\"SE-cbcd56f0-a6f3-4e03-b008-472732f793d6\"><span style=\"\" class=\"se-fs- se-ff-   \" id=\"SE-46823980-8069-4187-9cc8-2df10edf17d4\">등받이에 살짝 기대에 쉬는 느낌으로 앉아보세요!</span></p><!-- } SE-TEXT --><!-- SE-TEXT { --><p class=\"se-text-paragraph se-text-paragraph-align-center \" style=\"\" id=\"SE-fc6cfdee-3ed9-46bc-9124-1571e4b8dbcd\"><span style=\"\" class=\"se-fs- se-ff-   \" id=\"SE-956dc29d-cabc-4ee1-b7a1-093ff325b542\">​</span></p><!-- } SE-TEXT --><!-- SE-TEXT { --><p class=\"se-text-paragraph se-text-paragraph-align-center \" style=\"\" id=\"SE-92859049-855c-4904-abc5-ea7b1d9ca444\"><span style=\"\" class=\"se-fs- se-ff-   \" id=\"SE-09909c40-ab51-490a-8711-39857b528b82\">​</span></p><!-- } SE-TEXT -->\n                            </div>\n                        </div>\n                    </div>\n                </div>                <div class=\"se-component se-image se-l-default\" id=\"SE-8010a8d5-1dd2-42dc-98eb-25a390995227\">\n                    <div class=\"se-component-content se-component-content-fit\">\n                        <div class=\"se-section se-section-image se-l-default se-section-align-center\" >\n                                <div class=\"se-module se-module-image\" style=\"\">\n                                    <a href=\"#\" class=\"se-module-image-link __se_image_link __se_link\" style=\"\" onclick=\"return false;\" data-linktype=\"img\" data-linkdata='{\"id\" : \"SE-8010a8d5-1dd2-42dc-98eb-25a390995227\", \"src\" : \"https://isuhani-clinic-data.s3.ap-northeast-2.amazonaws.com/images/legacy/259832336282328a.png\", \"originalWidth\" : \"1080\", \"originalHeight\" : \"1080\", \"linkUse\" : \"false\", \"link\" : \"\"}'>\n                                        <img src=\"https://isuhani-clinic-data.s3.ap-northeast-2.amazonaws.com/images/legacy/259832336282328a.png\" data-lazy-src=\"https://isuhani-clinic-data.s3.ap-northeast-2.amazonaws.com/images/legacy/259832336282328a.png\" data-width=\"500\" data-height=\"500\" alt=\"\" class=\"se-image-resource\" />\n                                    </a>\n                                </div>\n                        </div>\n                    </div>\n                </div>\n                <div class=\"se-component se-text se-l-default\" id=\"SE-c0473249-14d4-4131-a202-b36eec3c853c\">\n                    <div class=\"se-component-content\">\n                        <div class=\"se-section se-section-text se-l-default\">\n                            <div class=\"se-module se-module-text\">\n                                    <!-- SE-TEXT { --><p class=\"se-text-paragraph se-text-paragraph-align-center \" style=\"\" id=\"SE-3d2e0a55-030d-4944-95ba-7ff191cd1595\"><span style=\"\" class=\"se-fs- se-ff-   \" id=\"SE-f39c3078-1a6d-4e1c-a62b-21b79bbd5e46\"><b>​</b></span></p><!-- } SE-TEXT --><!-- SE-TEXT { --><p class=\"se-text-paragraph se-text-paragraph-align-center \" style=\"\" id=\"SE-89134a87-0557-4934-990b-2771632ebdae\"><span style=\"background-color:#fff8b2;\" class=\"se-fs- se-ff-   \" id=\"SE-301f2e3b-05cb-4240-a0cf-f51ee90d2c73\"><b>3. 발은 지면에 닿도록 하자.</b></span></p><!-- } SE-TEXT --><!-- SE-TEXT { --><p class=\"se-text-paragraph se-text-paragraph-align-center \" style=\"\" id=\"SE-d009acd1-c8bd-4225-a087-15b1338ffdbd\"><span style=\"\" class=\"se-fs- se-ff-   \" id=\"SE-40cc1eb2-84ef-4e44-a908-e6fe4363c211\">​</span></p><!-- } SE-TEXT --><!-- SE-TEXT { --><p class=\"se-text-paragraph se-text-paragraph-align-center \" style=\"\" id=\"SE-e7d68a70-eccc-426f-a9e7-7bc748fcc30c\"><span style=\"\" class=\"se-fs- se-ff-   \" id=\"SE-ff40d838-f572-4b26-be24-f1b8eeea39d2\">의자에 앉았을 때,</span></p><!-- } SE-TEXT --><!-- SE-TEXT { --><p class=\"se-text-paragraph se-text-paragraph-align-center \" style=\"\" id=\"SE-5e12a877-de09-4eb5-924a-76e0fc1e10a2\"><span style=\"\" class=\"se-fs- se-ff-   \" id=\"SE-6d6d8293-ac02-44fc-a38e-a0a31798d929\">발이 공중에 떠있는 것보다,</span></p><!-- } SE-TEXT --><!-- SE-TEXT { --><p class=\"se-text-paragraph se-text-paragraph-align-center \" style=\"\" id=\"SE-385c9394-14dc-4372-a1b4-b7e0a142509c\"><span style=\"\" class=\"se-fs- se-ff-   \" id=\"SE-c8d9cd88-c052-4194-8e8c-eea1da7f8522\">지면에 닿은 채로 안정적인 자세를 유지하는 것이 좋습니다.</span></p><!-- } SE-TEXT --><!-- SE-TEXT { --><p class=\"se-text-paragraph se-text-paragraph-align-center \" style=\"\" id=\"SE-25f8b60f-e515-4b71-b7cd-b25f03c1c5fc\"><span style=\"\" class=\"se-fs- se-ff-   \" id=\"SE-c5174933-5ee8-4e65-9237-eaffb8f16f2e\">​</span></p><!-- } SE-TEXT --><!-- SE-TEXT { --><p class=\"se-text-paragraph se-text-paragraph-align-center \" style=\"\" id=\"SE-61e3cf6e-984a-41fe-8744-d055dc7bc499\"><span style=\"\" class=\"se-fs- se-ff-   \" id=\"SE-4886a271-7fe4-4f87-821b-7df1711f03e2\">의자가 너무 높을 경우에는 발 받침대 사용을 권장합니다.</span></p><!-- } SE-TEXT --><!-- SE-TEXT { --><p class=\"se-text-paragraph se-text-paragraph-align-center \" style=\"\" id=\"SE-4c6ca3c9-faff-4566-8f2f-910775eaa000\"><span style=\"\" class=\"se-fs- se-ff-   \" id=\"SE-b2b6b32a-249b-44cf-b876-763774a25b89\">​</span></p><!-- } SE-TEXT --><!-- SE-TEXT { --><p class=\"se-text-paragraph se-text-paragraph-align-center \" style=\"\" id=\"SE-d717693f-4198-466f-a895-78f7fcac9a6c\"><span style=\"\" class=\"se-fs- se-ff-   \" id=\"SE-eb32cbaf-304b-4340-bbaa-120a48744a4f\">​</span></p><!-- } SE-TEXT -->\n                            </div>\n                        </div>\n                    </div>\n                </div>                <div class=\"se-component se-image se-l-default\" id=\"SE-a3fabda7-5fad-4bda-a0fb-2b06f0012b5b\">\n                    <div class=\"se-component-content se-component-content-fit\">\n                        <div class=\"se-section se-section-image se-l-default se-section-align-center\" >\n                                <div class=\"se-module se-module-image\" style=\"\">\n                                    <a href=\"#\" class=\"se-module-image-link __se_image_link __se_link\" style=\"\" onclick=\"return false;\" data-linktype=\"img\" data-linkdata='{\"id\" : \"SE-a3fabda7-5fad-4bda-a0fb-2b06f0012b5b\", \"src\" : \"https://isuhani-clinic-data.s3.ap-northeast-2.amazonaws.com/images/legacy/d89f3a7750a19646.png\", \"originalWidth\" : \"1080\", \"originalHeight\" : \"1080\", \"linkUse\" : \"false\", \"link\" : \"\"}'>\n                                        <img src=\"https://isuhani-clinic-data.s3.ap-northeast-2.amazonaws.com/images/legacy/d89f3a7750a19646.png\" data-lazy-src=\"https://isuhani-clinic-data.s3.ap-northeast-2.amazonaws.com/images/legacy/d89f3a7750a19646.png\" data-width=\"500\" data-height=\"500\" alt=\"\" class=\"se-image-resource\" />\n                                    </a>\n                                </div>\n                        </div>\n                    </div>\n                </div>\n                <div class=\"se-component se-text se-l-default\" id=\"SE-21fed7ac-4514-4827-8cde-f7a8e3432b1f\">\n                    <div class=\"se-component-content\">\n                        <div class=\"se-section se-section-text se-l-default\">\n                            <div class=\"se-module se-module-text\">\n                                    <!-- SE-TEXT { --><p class=\"se-text-paragraph se-text-paragraph-align-center \" style=\"\" id=\"SE-0a25aa68-b583-44e7-857c-df0e2f1fa5fb\"><span style=\"\" class=\"se-fs- se-ff-   \" id=\"SE-8fe7286f-8067-4638-bbf4-3771c47f8d4a\"><b>​</b></span></p><!-- } SE-TEXT --><!-- SE-TEXT { --><p class=\"se-text-paragraph se-text-paragraph-align-center \" style=\"\" id=\"SE-12c41137-1f2c-4125-b684-62eec569f8ab\"><span style=\"background-color:#fff8b2;\" class=\"se-fs- se-ff-   \" id=\"SE-5b90af7a-389e-4ed9-ac0b-6e252e8ab399\"><b>4. 등을 등받이에 붙이고 턱은 살짝 당겨준다.</b></span></p><!-- } SE-TEXT --><!-- SE-TEXT { --><p class=\"se-text-paragraph se-text-paragraph-align-center \" style=\"\" id=\"SE-2f398b7e-e48c-4deb-9584-9b0e5113f542\"><span style=\"\" class=\"se-fs- se-ff-   \" id=\"SE-631f8d68-7883-477e-af44-bd8d8559806f\">​</span></p><!-- } SE-TEXT --><!-- SE-TEXT { --><p class=\"se-text-paragraph se-text-paragraph-align-center \" style=\"\" id=\"SE-cd6885ca-81e8-42f3-9e70-b52695e16612\"><span style=\"\" class=\"se-fs- se-ff-   \" id=\"SE-90f210b9-4582-4ac8-8cc7-f3f891189431\">의자에 앉았다면,</span></p><!-- } SE-TEXT --><!-- SE-TEXT { --><p class=\"se-text-paragraph se-text-paragraph-align-center \" style=\"\" id=\"SE-751e42af-6b47-41a8-b7a7-31163eac18f3\"><span style=\"\" class=\"se-fs- se-ff-   \" id=\"SE-5499e2bc-cd22-4c1b-84a0-fd6473e2b98a\">등은 등받이에 살포시 붙이고,</span></p><!-- } SE-TEXT --><!-- SE-TEXT { --><p class=\"se-text-paragraph se-text-paragraph-align-center \" style=\"\" id=\"SE-1a57da62-1b88-4ab0-a042-017bcb537463\"><span style=\"\" class=\"se-fs- se-ff-   \" id=\"SE-e237368c-a7d2-4e97-b3ea-a76fd9c06bf7\">턱은 살짝 당겨주는 것이 가장 올바른 자세인데요,</span></p><!-- } SE-TEXT --><!-- SE-TEXT { --><p class=\"se-text-paragraph se-text-paragraph-align-center \" style=\"\" id=\"SE-181e93c0-32b2-4098-bb2b-6800a9ca0ce2\"><span style=\"\" class=\"se-fs- se-ff-   \" id=\"SE-a32345b3-9f84-4307-85f2-0461684ff0cb\">​</span></p><!-- } SE-TEXT --><!-- SE-TEXT { --><p class=\"se-text-paragraph se-text-paragraph-align-center \" style=\"\" id=\"SE-0508a24e-075b-4fc5-97cf-8099d2c743c0\"><span style=\"\" class=\"se-fs- se-ff-   \" id=\"SE-7759464f-1857-40ee-becf-b4e24f354f20\">처음에는 다소 불편하게 느껴지는 자세이지만,</span></p><!-- } SE-TEXT --><!-- SE-TEXT { --><p class=\"se-text-paragraph se-text-paragraph-align-center \" style=\"\" id=\"SE-69d0b4d7-f9ea-4286-bc60-143d72dc4b2b\"><span style=\"\" class=\"se-fs- se-ff-   \" id=\"SE-e55c68af-82d3-46d3-9fb7-190214f97f55\">점차 익숙해지면서 자세 교정이 이루어지게 됩니다.</span></p><!-- } SE-TEXT --><!-- SE-TEXT { --><p class=\"se-text-paragraph se-text-paragraph-align-center \" style=\"\" id=\"SE-9368b697-a3fb-47c2-9d75-77a2963b90a9\"><span style=\"\" class=\"se-fs- se-ff-   \" id=\"SE-8117fb29-1594-4503-a963-dd8545722a27\">​</span></p><!-- } SE-TEXT --><!-- SE-TEXT { --><p class=\"se-text-paragraph se-text-paragraph-align-center \" style=\"\" id=\"SE-cfbbadd9-deb1-422d-804f-d05154fa3cb6\"><span style=\"\" class=\"se-fs- se-ff-   \" id=\"SE-7c333fc7-861e-451f-aa2f-d7e4037dda63\">​</span></p><!-- } SE-TEXT -->\n                            </div>\n                        </div>\n                    </div>\n                </div>                <div class=\"se-component se-image se-l-default\" id=\"SE-865dc359-efdf-488c-a540-03fbcf45ec29\">\n                    <div class=\"se-component-content se-component-content-fit\">\n                        <div class=\"se-section se-section-image se-l-default se-section-align-center\" >\n                                <div class=\"se-module se-module-image\" style=\"\">\n                                    <a href=\"#\" class=\"se-module-image-link __se_image_link __se_link\" style=\"\" onclick=\"return false;\" data-linktype=\"img\" data-linkdata='{\"id\" : \"SE-865dc359-efdf-488c-a540-03fbcf45ec29\", \"src\" : \"https://isuhani-clinic-data.s3.ap-northeast-2.amazonaws.com/images/legacy/28ab5a608670bfe7.png\", \"originalWidth\" : \"1080\", \"originalHeight\" : \"1080\", \"linkUse\" : \"false\", \"link\" : \"\"}'>\n                                        <img src=\"https://isuhani-clinic-data.s3.ap-northeast-2.amazonaws.com/images/legacy/28ab5a608670bfe7.png\" data-lazy-src=\"https://isuhani-clinic-data.s3.ap-northeast-2.amazonaws.com/images/legacy/28ab5a608670bfe7.png\" data-width=\"500\" data-height=\"500\" alt=\"\" class=\"se-image-resource\" />\n                                    </a>\n                                </div>\n                        </div>\n                    </div>\n                </div>\n                <div class=\"se-component se-text se-l-default\" id=\"SE-8f0f42f5-3d61-4a62-9995-f40bcff4f158\">\n                    <div class=\"se-component-content\">\n                        <div class=\"se-section se-section-text se-l-default\">\n                            <div class=\"se-module se-module-text\">\n                                    <!-- SE-TEXT { --><p class=\"se-text-paragraph se-text-paragraph-align-center \" style=\"\" id=\"SE-b8fd038a-3128-4bd3-a3d6-03857f6c9b4b\"><span style=\"\" class=\"se-fs- se-ff-   \" id=\"SE-885800f1-03a2-49f7-9f6b-8f94d2cb63bf\"><b>​</b></span></p><!-- } SE-TEXT --><!-- SE-TEXT { --><p class=\"se-text-paragraph se-text-paragraph-align-center \" style=\"\" id=\"SE-8cfc1d9f-1314-4ddf-9c30-0048d0375951\"><span style=\"background-color:#fff8b2;\" class=\"se-fs- se-ff-   \" id=\"SE-7291e884-8db9-4e4d-a357-aea0a79c4eee\"><b>5. 책상을 알맞은 높이로 조절한다.</b></span></p><!-- } SE-TEXT --><!-- SE-TEXT { --><p class=\"se-text-paragraph se-text-paragraph-align-center \" style=\"\" id=\"SE-a6680346-e544-471b-92cc-fc980b6aa513\"><span style=\"\" class=\"se-fs- se-ff-   \" id=\"SE-4df5209c-5e3a-4de7-be1e-4cb16fa12d25\">​</span></p><!-- } SE-TEXT --><!-- SE-TEXT { --><p class=\"se-text-paragraph se-text-paragraph-align-center \" style=\"\" id=\"SE-a2fdbb25-800f-400d-91d0-004d057ef589\"><span style=\"\" class=\"se-fs- se-ff-   \" id=\"SE-b1962296-22dd-4ebe-9377-c9495396d996\">책상이 너무 높아도, 너무 낮아도</span></p><!-- } SE-TEXT --><!-- SE-TEXT { --><p class=\"se-text-paragraph se-text-paragraph-align-center \" style=\"\" id=\"SE-3a382864-6215-4f04-817d-1eb20657ed14\"><span style=\"\" class=\"se-fs- se-ff-   \" id=\"SE-5c5d96c9-a00e-4ea0-b8ce-4914e9a3c88b\">우리의 목에 무리가 가게 될 수 있습니다.</span></p><!-- } SE-TEXT --><!-- SE-TEXT { --><p class=\"se-text-paragraph se-text-paragraph-align-center \" style=\"\" id=\"SE-b3664933-15fa-40c6-a246-009ce1918886\"><span style=\"\" class=\"se-fs- se-ff-   \" id=\"SE-2b298370-5f03-4da3-802c-ed71b33d24e0\">​</span></p><!-- } SE-TEXT --><!-- SE-TEXT { --><p class=\"se-text-paragraph se-text-paragraph-align-center \" style=\"\" id=\"SE-f30b882d-a217-45e4-b1ab-4d391b25ccff\"><span style=\"\" class=\"se-fs- se-ff-   \" id=\"SE-a0363e58-8e2a-48e9-be23-a42575d779a4\">책상의 높이는 팔꿈치를 가볍게 올려놓을 수 있는</span></p><!-- } SE-TEXT --><!-- SE-TEXT { --><p class=\"se-text-paragraph se-text-paragraph-align-center \" style=\"\" id=\"SE-c999ce31-4484-4a01-8915-976bf34e33e6\"><span style=\"\" class=\"se-fs- se-ff-   \" id=\"SE-61194eab-cc00-4835-aad1-ad83d0b7cde8\">높이가 가장 적당합니다.</span></p><!-- } SE-TEXT --><!-- SE-TEXT { --><p class=\"se-text-paragraph se-text-paragraph-align-center \" style=\"\" id=\"SE-c77e9529-416c-4b90-81f4-2f3fb1c1bd81\"><span style=\"\" class=\"se-fs- se-ff-   \" id=\"SE-2719a1f6-6ca0-4c8c-8907-ea27312010fe\">​</span></p><!-- } SE-TEXT --><!-- SE-TEXT { --><p class=\"se-text-paragraph se-text-paragraph-align-center \" style=\"\" id=\"SE-42765b8d-807b-40c2-9a1b-8022bd3fa88a\"><span style=\"\" class=\"se-fs- se-ff-   \" id=\"SE-177bb722-eb70-4763-8db9-fe3ceb306c37\">​</span></p><!-- } SE-TEXT -->\n                            </div>\n                        </div>\n                    </div>\n                </div>                <div class=\"se-component se-image se-l-default\" id=\"SE-a890b37f-8675-47cb-9626-3ef8a88759eb\">\n                    <div class=\"se-component-content se-component-content-fit\">\n                        <div class=\"se-section se-section-image se-l-default se-section-align-center\" >\n                                <div class=\"se-module se-module-image\" style=\"\">\n                                    <a href=\"#\" class=\"se-module-image-link __se_image_link __se_link\" style=\"\" onclick=\"return false;\" data-linktype=\"img\" data-linkdata='{\"id\" : \"SE-a890b37f-8675-47cb-9626-3ef8a88759eb\", \"src\" : \"https://isuhani-clinic-data.s3.ap-northeast-2.amazonaws.com/images/legacy/f3054efd2ce1d1a2.png\", \"originalWidth\" : \"1080\", \"originalHeight\" : \"1080\", \"linkUse\" : \"false\", \"link\" : \"\"}'>\n                                        <img src=\"https://isuhani-clinic-data.s3.ap-northeast-2.amazonaws.com/images/legacy/f3054efd2ce1d1a2.png\" data-lazy-src=\"https://isuhani-clinic-data.s3.ap-northeast-2.amazonaws.com/images/legacy/f3054efd2ce1d1a2.png\" data-width=\"500\" data-height=\"500\" alt=\"\" class=\"se-image-resource\" />\n                                    </a>\n                                </div>\n                        </div>\n                    </div>\n                </div>\n                <div class=\"se-component se-text se-l-default\" id=\"SE-9bb54f41-93d0-4b5e-9db3-4d053ed9dd57\">\n                    <div class=\"se-component-content\">\n                        <div class=\"se-section se-section-text se-l-default\">\n                            <div class=\"se-module se-module-text\">\n                                    <!-- SE-TEXT { --><p class=\"se-text-paragraph se-text-paragraph-align-center \" style=\"\" id=\"SE-831a8b99-121e-4ddf-8df5-c76878d6b7ca\"><span style=\"\" class=\"se-fs- se-ff-   \" id=\"SE-71f7a05a-2d7a-4c3a-98c7-0ccbfa795760\">​</span></p><!-- } SE-TEXT --><!-- SE-TEXT { --><p class=\"se-text-paragraph se-text-paragraph-align-center \" style=\"\" id=\"SE-1b3848c4-df4a-4a83-af05-4c90bdde3ff6\"><span style=\"\" class=\"se-fs- se-ff-   \" id=\"SE-486e1dc0-eaef-4cdb-82e8-5940adf8d5f0\">이렇게 일자목을 탈출하기 위한</span></p><!-- } SE-TEXT --><!-- SE-TEXT { --><p class=\"se-text-paragraph se-text-paragraph-align-center \" style=\"\" id=\"SE-22b2b11d-8c23-4829-bdb5-98e1dd82f663\"><span style=\"\" class=\"se-fs- se-ff-   \" id=\"SE-09e6b4b2-d1f7-4858-8d14-618e36c3a107\">바른 생활습관들을 정리해보았습니다!</span></p><!-- } SE-TEXT --><!-- SE-TEXT { --><p class=\"se-text-paragraph se-text-paragraph-align-center \" style=\"\" id=\"SE-b0213466-ae40-4f2b-9908-cb73228cd569\"><span style=\"\" class=\"se-fs- se-ff-   \" id=\"SE-021677e5-2d45-452b-b504-8bf9c0ce0f45\">꼭 기억하시고, 함께 일자목 탈출해보아요 :)</span></p><!-- } SE-TEXT --><!-- SE-TEXT { --><p class=\"se-text-paragraph se-text-paragraph-align-center \" style=\"\" id=\"SE-07b820be-3f10-4f34-ac38-a6ee8bc85225\"><span style=\"color:#222222;\" class=\"se-fs-fs11 se-ff-nanumgothic  se-style-unset \" id=\"SE-7a0ad6e1-6590-45bc-a927-8675b5dd815d\"><u>​</u></span></p><!-- } SE-TEXT --><!-- SE-TEXT { --><p class=\"se-text-paragraph se-text-paragraph-align-center \" style=\"\" id=\"SE-c1bff937-53e5-4ab6-813a-80b764364481\"><span style=\"color:#222222;\" class=\"se-fs-fs11 se-ff-nanumgothic  se-style-unset \" id=\"SE-b85aa439-7974-421e-b5e0-f52089c38c68\"><u>​</u></span></p><!-- } SE-TEXT -->\n                            </div>\n                        </div>\n                    </div>\n                </div>                <div class=\"se-component se-oembed se-l-default\" id=\"SE-d1e883f6-6ee6-48b8-90a8-df8ba4a0ca67\">\n                    <div class=\"se-component-content se-component-content-fit\">\n                        <div class=\"se-section se-section-oembed se-section-align-center se-l-default\">\n                            <div class=\"se-module se-module-oembed se-is-progress\" style=\"padding-top: 56.25%;\"></div>\n                        </div>\n                    </div>\n                    <script type=\"text/data\" class=\"__se_module_data\" data-module='{\"type\":\"v2_oembed\", \"id\" :\"SE-d1e883f6-6ee6-48b8-90a8-df8ba4a0ca67\", \"data\" : { \"html\": &quot;&lt;iframe width&#x3D;&#x27;544&#x27; height&#x3D;&#x27;306&#x27; src&#x3D;&#x27;https://tv.naver.com/embed/24006997?autoPlay&#x3D;false&amp;oNm&#x3D;outKeyPlayer.nhn&#x27; frameborder&#x3D;&#x27;0&#x27; allowfullscreen&gt;&lt;/iframe&gt;&quot;, \"originalWidth\" : \"544\", \"originalHeight\" : \"306\", \"contentMode\" : \"fit\", \"description\": &quot;이수한의원 | ‘못도 씹어 먹겠다.’ ‘소도 때려잡겠다.’ 그렇다. 젊다는 것은 활기차고 팔팔함을 의미한다. 못 할 것 같 은 일이 없어야 한다. 한숨 자고 일어나면 피곤함도 싹 사라진다. 그런데 과연 현실은 그럴까? 요즘 사람들은 전혀 아닌 것 같다. 20대에 허리 디스크로 수술을 하는 사람들이 있는가 하면, 30~ 40대 직장인들은 일자목 뼈 변형과 목 디스크를 직업병인 것 마냥 안고 산다. 대체 왜 젊음으로도 못 버틸 이런 일들이 일어났을까? 그 이유로는 잘못된 식습관, 과로, 스트레스, 운동 부족 등 여러가지를 들 수 있을 ...&quot;, \"inputUrl\": \"https://tv.naver.com/v/24006997\", \"thumbnailUrl\" : \"https://isuhani-clinic-data.s3.ap-northeast-2.amazonaws.com/images/legacy/e285264f4690c98a.jpg\", \"thumbnailHeight\" : \"388\", \"thumbnailWidth\" : \"699\", \"title\": &quot;[한방토크] 20대 허리디스크 일자목 전성시대&quot;, \"providerUrl\": \"https://tv.naver.com\", \"align\": \"center\", \"type\" : \"video\" }}'></script>\n                </div>\n                \n                <div class=\"se-component se-text se-l-default\" id=\"SE-d9a41e57-c5ef-4275-ba89-3ff60c1d16f1\">\n                    <div class=\"se-component-content\">\n                        <div class=\"se-section se-section-text se-l-default\">\n                            <div class=\"se-module se-module-text\">\n                                    <!-- SE-TEXT { --><p class=\"se-text-paragraph se-text-paragraph-align-center \" style=\"\" id=\"SE-3554e829-cf71-46a2-8a3f-3ba898dba5ad\"><span style=\"\" class=\"se-fs- se-ff-   \" id=\"SE-fd9e6dd0-f593-4128-abcf-9624b163135c\">​</span></p><!-- } SE-TEXT -->\n                            </div>\n                        </div>\n                    </div>\n                </div>                <div class=\"se-component se-horizontalLine se-l-default\" id=\"SE-6b26d774-97c2-4f97-af0f-849d2698c3f1\">\n                    <div class=\"se-component-content\">\n                        <div class=\"se-section se-section-horizontalLine se-l-default se-section-align-center\">\n                            <div class=\"se-module se-module-horizontalLine\">\n                                <hr class=\"se-hr\" />\n                            </div>\n                        </div>\n                    </div>\n                </div>                <div class=\"se-component se-text se-l-default\" id=\"SE-2e79f75c-ae52-4815-a13b-157c4fc7ad88\">\n                    <div class=\"se-component-content\">\n                        <div class=\"se-section se-section-text se-l-default\">\n                            <div class=\"se-module se-module-text\">\n                                    <!-- SE-TEXT { --><p class=\"se-text-paragraph se-text-paragraph-align-center \" style=\"\" id=\"SE-a6a6b75d-449a-45f4-9285-8e83bd1525cd\"><span style=\"\" class=\"se-fs- se-ff-   \" id=\"SE-3af2be68-7f79-44c6-a2f3-0767cd471c2a\">오늘 여러분과 함께</span></p><!-- } SE-TEXT --><!-- SE-TEXT { --><p class=\"se-text-paragraph se-text-paragraph-align-center \" style=\"\" id=\"SE-38564bac-4b1e-469b-ad9a-61ff7a9e307e\"><span style=\"\" class=\"se-fs- se-ff-   \" id=\"SE-8a1f9e4c-1fb5-450c-bdf5-8688446974ce\">통증해결 한방토크 그 첫 번째 시간,</span></p><!-- } SE-TEXT --><!-- SE-TEXT { --><p class=\"se-text-paragraph se-text-paragraph-align-center \" style=\"\" id=\"SE-68cf42f4-3c5c-432a-8e44-f4c00deb3741\"><span style=\"\" class=\"se-fs- se-ff-   \" id=\"SE-dc1bd482-c96b-45d1-8e9f-3654061f9314\">&#x27;일자목 탈출 방법&#x27;에 대해 알아보았습니다.</span></p><!-- } SE-TEXT --><!-- SE-TEXT { --><p class=\"se-text-paragraph se-text-paragraph-align-center \" style=\"\" id=\"SE-29aa0b40-ecce-45a5-9375-7670f400e631\"><span style=\"\" class=\"se-fs- se-ff-   \" id=\"SE-99bad254-becd-4ecf-94f5-23fde68d29df\">​</span></p><!-- } SE-TEXT --><!-- SE-TEXT { --><p class=\"se-text-paragraph se-text-paragraph-align-center \" style=\"\" id=\"SE-df766ad8-2ddc-4af5-9a02-751c8247ec1b\"><span style=\"\" class=\"se-fs- se-ff-   \" id=\"SE-b1015eaa-6089-4761-a8f1-8ce62896562b\">다음에는 또 다른 좋은 정보로 돌아오겠습니다!</span></p><!-- } SE-TEXT --><!-- SE-TEXT { --><p class=\"se-text-paragraph se-text-paragraph-align-center \" style=\"\" id=\"SE-c2caa038-ef08-4f4e-8448-0c7973fe5006\"><span style=\"color:#222222;\" class=\"se-fs-fs11 se-ff-nanumgothic  se-style-unset \" id=\"SE-d17db324-6617-437b-9d84-85421b2315af\"><u>​</u></span></p><!-- } SE-TEXT -->\n                            </div>\n                        </div>\n                    </div>\n                </div>                <div class=\"se-component se-image se-l-default\" id=\"SE-2a24b98d-83d4-4fbd-8c3f-fa4087a3fa71\">\n                    <div class=\"se-component-content se-component-content-fit\">\n                        <div class=\"se-section se-section-image se-l-default se-section-align-center\" >\n                                <div class=\"se-module se-module-image\" style=\"\">\n                                    <a href=\"#\" class=\"se-module-image-link __se_image_link __se_link\" style=\"\" onclick=\"return false;\" data-linktype=\"img\" data-linkdata='{\"id\" : \"SE-2a24b98d-83d4-4fbd-8c3f-fa4087a3fa71\", \"src\" : \"https://isuhani-clinic-data.s3.ap-northeast-2.amazonaws.com/images/legacy/f68b6bd945758783.jpg\", \"originalWidth\" : \"1000\", \"originalHeight\" : \"1000\", \"linkUse\" : \"false\", \"link\" : \"\"}'>\n                                        <img src=\"https://isuhani-clinic-data.s3.ap-northeast-2.amazonaws.com/images/legacy/f68b6bd945758783.jpg\" data-lazy-src=\"https://isuhani-clinic-data.s3.ap-northeast-2.amazonaws.com/images/legacy/f68b6bd945758783.jpg\" data-width=\"500\" data-height=\"500\" alt=\"\" class=\"se-image-resource\" />\n                                    </a>\n                                </div>\n                        </div>\n                    </div>\n                </div>\n                <div class=\"se-component se-placesMap se-l-default\" id=\"SE-91f69b4b-e165-46c9-af10-a0546144a5fb\">\n                    <div class=\"se-component-content\">\n                        <div class=\"se-section se-section-placesMap  se-section-align-center se-l-default\">\n                            <div class=\"se-module se-module-map-image\">\n                                <img src=\"https://simg.pstatic.net/static.map/v2/map/staticmap.bin?caller&#x3D;smarteditor&amp;markers&#x3D;color%3A0x11cc73%7Csize%3Amid%7Cpos%3A126.9721638%2037.484007%7CviewSizeRatio%3A0.6%7Ctype%3Ad&amp;w&#x3D;700&amp;h&#x3D;315&amp;scale&#x3D;1\" alt=\"\" class=\"se-map-image\" />\n                            </div>\n                                <div class=\"se-module se-module-map-text \">\n                                        <a href=\"#\" target=\"_blank\" class=\"se-map-info __se_link\" onclick=\"return false;\" data-linktype=\"map\" data-linkdata='{\"eventTarget\" : \"placeDesc\", \"placeId\" : \"13104608\", \"searchEngine\" : \"naver\", \"searchType\" : \"s\", \"name\" : \"이수한의원\", \"address\" : \"서울특별시 동작구 사당로 218-1 2층\", \"latitude\" : \"37.484007\", \"longitude\" : \"126.9721638\", \"tel\" : \"0507-1344-1075\", \"bookingUrl\" : \"https://booking.naver.com/booking/13/bizes/331349\" }'>\n                                        <strong class=\"se-map-title\">이수한의원</strong>\n                                        <p class=\"se-map-address\">서울특별시 동작구 사당로 218-1 2층</p>\n                                    </a>\n                                </div>\n                        </div>\n                    </div>\n                    <script type=\"text/data\" class=\"__se_module_data\" data-module='{\"type\":\"v2_map\", \"id\" :\"SE-91f69b4b-e165-46c9-af10-a0546144a5fb\", \"data\" : { \"layout\": \"default\", \"searchEngine\" : \"naver\", \"places\" : [{\"placeId\":\"13104608\",\"name\":\"이수한의원\",\"address\":\"서울특별시 동작구 사당로 218-1 2층\",\"latlng\":{\"@ctype\":\"position\",\"latitude\":37.484007,\"longitude\":126.9721638},\"searchType\":\"s\",\"tel\":\"0507-1344-1075\",\"bookingUrl\":\"https://booking.naver.com/booking/13/bizes/331349\"}] }}'></script>\n                </div>                <div class=\"se-component se-image se-l-default\" id=\"SE-86bc689e-821d-4733-93b0-2ee077e6db1d\">\n                    <div class=\"se-component-content se-component-content-fit\">\n                        <div class=\"se-section se-section-image se-l-default se-section-align-center\" >\n                                <div class=\"se-module se-module-image\" style=\"\">\n                                    <a href=\"#\" class=\"se-module-image-link-use se-module-image-link __se_image_link __se_link\" style=\"\" onclick=\"return false;\" data-linktype=\"img\" data-linkdata='{\"id\" : \"SE-86bc689e-821d-4733-93b0-2ee077e6db1d\", \"src\" : \"https://isuhani-clinic-data.s3.ap-northeast-2.amazonaws.com/images/legacy/3467a1a7ce872d98.png\", \"originalWidth\" : \"747\", \"originalHeight\" : \"308\", \"linkUse\" : \"true\", \"link\" : \"https://talk.naver.com/ct/w4vt4b?frm&#x3D;mnmb&amp;frm&#x3D;nmb_detail\"}'>\n                                        <img src=\"https://isuhani-clinic-data.s3.ap-northeast-2.amazonaws.com/images/legacy/3467a1a7ce872d98.png\" data-lazy-src=\"https://isuhani-clinic-data.s3.ap-northeast-2.amazonaws.com/images/legacy/3467a1a7ce872d98.png\" data-width=\"500\" data-height=\"206\" alt=\"\" class=\"se-image-resource\" />\n                                    </a>\n                                </div>\n                        </div>\n                    </div>\n                </div>\n                <div class=\"se-component se-text se-l-default\" id=\"SE-26dd6309-1e64-48b7-a3b9-f99f15370afd\">\n                    <div class=\"se-component-content\">\n                        <div class=\"se-section se-section-text se-l-default\">\n                            <div class=\"se-module se-module-text\">\n                                    <!-- SE-TEXT { --><p class=\"se-text-paragraph se-text-paragraph-align- \" style=\"\" id=\"SE-03ffc141-d0cc-42eb-be81-eefc1bb0fb62\"><span style=\"\" class=\"se-fs- se-ff-   \" id=\"SE-edc3769d-7851-4570-ac11-694e73f97768\">​</span></p><!-- } SE-TEXT -->\n                            </div>\n                        </div>\n                    </div>\n                </div>    </div>",
  "body_kind": "html",
  "images": [
    "https://isuhani-clinic-data.s3.ap-northeast-2.amazonaws.com/images/legacy/e285264f4690c98a.jpg",
    "https://isuhani-clinic-data.s3.ap-northeast-2.amazonaws.com/images/legacy/c147a1acd7415621.png",
    "https://isuhani-clinic-data.s3.ap-northeast-2.amazonaws.com/images/legacy/c147a1acd7415621.png",
    "https://isuhani-clinic-data.s3.ap-northeast-2.amazonaws.com/images/legacy/c147a1acd7415621.png",
    "https://isuhani-clinic-data.s3.ap-northeast-2.amazonaws.com/images/legacy/d6325549376bb399.png",
    "https://isuhani-clinic-data.s3.ap-northeast-2.amazonaws.com/images/legacy/d6325549376bb399.png",
    "https://isuhani-clinic-data.s3.ap-northeast-2.amazonaws.com/images/legacy/d6325549376bb399.png",
    "https://isuhani-clinic-data.s3.ap-northeast-2.amazonaws.com/images/legacy/5fccecb0fbec324a.png",
    "https://isuhani-clinic-data.s3.ap-northeast-2.amazonaws.com/images/legacy/5fccecb0fbec324a.png",
    "https://isuhani-clinic-data.s3.ap-northeast-2.amazonaws.com/images/legacy/5fccecb0fbec324a.png",
    "https://isuhani-clinic-data.s3.ap-northeast-2.amazonaws.com/images/legacy/685885ca3abd76e2.png",
    "https://isuhani-clinic-data.s3.ap-northeast-2.amazonaws.com/images/legacy/685885ca3abd76e2.png",
    "https://isuhani-clinic-data.s3.ap-northeast-2.amazonaws.com/images/legacy/685885ca3abd76e2.png",
    "https://isuhani-clinic-data.s3.ap-northeast-2.amazonaws.com/images/legacy/28ab5a608670bfe7.png",
    "https://isuhani-clinic-data.s3.ap-northeast-2.amazonaws.com/images/legacy/28ab5a608670bfe7.png",
    "https://isuhani-clinic-data.s3.ap-northeast-2.amazonaws.com/images/legacy/28ab5a608670bfe7.png",
    "https://isuhani-clinic-data.s3.ap-northeast-2.amazonaws.com/images/legacy/42842e8d70644435.png",
    "https://isuhani-clinic-data.s3.ap-northeast-2.amazonaws.com/images/legacy/42842e8d70644435.png",
    "https://isuhani-clinic-data.s3.ap-northeast-2.amazonaws.com/images/legacy/42842e8d70644435.png",
    "https://isuhani-clinic-data.s3.ap-northeast-2.amazonaws.com/images/legacy/bf8e71933c5f0ace.png",
    "https://isuhani-clinic-data.s3.ap-northeast-2.amazonaws.com/images/legacy/bf8e71933c5f0ace.png",
    "https://isuhani-clinic-data.s3.ap-northeast-2.amazonaws.com/images/legacy/bf8e71933c5f0ace.png",
    "https://isuhani-clinic-data.s3.ap-northeast-2.amazonaws.com/images/legacy/259832336282328a.png",
    "https://isuhani-clinic-data.s3.ap-northeast-2.amazonaws.com/images/legacy/259832336282328a.png",
    "https://isuhani-clinic-data.s3.ap-northeast-2.amazonaws.com/images/legacy/259832336282328a.png",
    "https://isuhani-clinic-data.s3.ap-northeast-2.amazonaws.com/images/legacy/030e006f9a4a6668.png",
    "https://isuhani-clinic-data.s3.ap-northeast-2.amazonaws.com/images/legacy/030e006f9a4a6668.png",
    "https://isuhani-clinic-data.s3.ap-northeast-2.amazonaws.com/images/legacy/030e006f9a4a6668.png",
    "https://isuhani-clinic-data.s3.ap-northeast-2.amazonaws.com/images/legacy/d89f3a7750a19646.png",
    "https://isuhani-clinic-data.s3.ap-northeast-2.amazonaws.com/images/legacy/d89f3a7750a19646.png",
    "https://isuhani-clinic-data.s3.ap-northeast-2.amazonaws.com/images/legacy/d89f3a7750a19646.png",
    "https://isuhani-clinic-data.s3.ap-northeast-2.amazonaws.com/images/legacy/f68b6bd945758783.jpg",
    "https://isuhani-clinic-data.s3.ap-northeast-2.amazonaws.com/images/legacy/f68b6bd945758783.jpg",
    "https://isuhani-clinic-data.s3.ap-northeast-2.amazonaws.com/images/legacy/f68b6bd945758783.jpg",
    "https://isuhani-clinic-data.s3.ap-northeast-2.amazonaws.com/images/legacy/e3a736e8df22f0b4.png",
    "https://isuhani-clinic-data.s3.ap-northeast-2.amazonaws.com/images/legacy/e3a736e8df22f0b4.png",
    "https://isuhani-clinic-data.s3.ap-northeast-2.amazonaws.com/images/legacy/e3a736e8df22f0b4.png",
    "https://isuhani-clinic-data.s3.ap-northeast-2.amazonaws.com/images/legacy/f3054efd2ce1d1a2.png",
    "https://isuhani-clinic-data.s3.ap-northeast-2.amazonaws.com/images/legacy/f3054efd2ce1d1a2.png",
    "https://isuhani-clinic-data.s3.ap-northeast-2.amazonaws.com/images/legacy/f3054efd2ce1d1a2.png",
    "https://isuhani-clinic-data.s3.ap-northeast-2.amazonaws.com/images/legacy/3467a1a7ce872d98.png",
    "https://isuhani-clinic-data.s3.ap-northeast-2.amazonaws.com/images/legacy/3467a1a7ce872d98.png",
    "https://isuhani-clinic-data.s3.ap-northeast-2.amazonaws.com/images/legacy/3467a1a7ce872d98.png",
    "https://isuhani-clinic-data.s3.ap-northeast-2.amazonaws.com/images/legacy/b5f4853be314d8da.png",
    "https://isuhani-clinic-data.s3.ap-northeast-2.amazonaws.com/images/legacy/b5f4853be314d8da.png",
    "https://isuhani-clinic-data.s3.ap-northeast-2.amazonaws.com/images/legacy/b5f4853be314d8da.png",
    "https://isuhani-clinic-data.s3.ap-northeast-2.amazonaws.com/images/legacy/f9d3c3299e02cb19.png"
  ],
  "meta": {
    "ogTitle": "20대 허리디스크 일자목 전성시대",
    "ogDesc": "통증과 체형을 한번에! 몸과 마음의 균형! 안녕하세요, 이수한의원입니다. 오늘은 통증해결 한방토크 첫 번...",
    "ogImage": "https://isuhani-clinic-data.s3.ap-northeast-2.amazonaws.com/images/legacy/f9d3c3299e02cb19.png",
    "category": "한의원 story",
    "date": "2021-12-02"
  }
}