{
  "logNo": "223156104786",
  "blog": "metroparis",
  "title": "이수역 한의원 여름 보약, 생맥산",
  "addDate": "2023. 7. 14.",
  "categoryNo": "",
  "parentCategoryNo": "",
  "url": "https://blog.naver.com/PostView.naver?blogId=metroparis&logNo=223156104786",
  "blocks": [],
  "body": "<div class=\"se-main-container\">\n                <div class=\"se-component se-text se-l-default\" id=\"SE-2d689a81-1b0e-4333-ae69-14dd6f9d366f\">\n                    <div class=\"se-component-content\">\n                        <div class=\"se-section se-section-text se-l-default\">\n                            <div class=\"se-module se-module-text\">\n                                    <!-- SE-TEXT { --><p class=\"se-text-paragraph se-text-paragraph-align- \" style=\"\" id=\"SE-3DDECD75-EA78-49B4-B79C-79CC64ACF655\"><span style=\"\" class=\"se-fs- se-ff-   \" id=\"SE-2799B02D-2107-4F7F-A4EE-2E9580CACB0C\">​</span></p><!-- } SE-TEXT -->\n                            </div>\n                        </div>\n                    </div>\n                </div>                <div class=\"se-component se-image se-l-default\" id=\"SE-f279a0dc-3531-41bc-b997-90d9963cb57d\">\n                    <div class=\"se-component-content se-component-content-normal\">\n                        <div class=\"se-section se-section-image se-l-default se-section-align-center\" style=\"max-width:254px;\">\n                                <div class=\"se-module se-module-image\" style=\"\">\n                                    <a href=\"#\" class=\"se-module-image-link __se_image_link __se_link\" style=\"\" onclick=\"return false;\" data-linktype=\"img\" data-linkdata='{\"id\" : \"SE-f279a0dc-3531-41bc-b997-90d9963cb57d\", \"src\" : \"https://isuhani-clinic-data.s3.ap-northeast-2.amazonaws.com/images/legacy/d721f1ec30328972.png\", \"originalWidth\" : \"494\", \"originalHeight\" : \"97\", \"linkUse\" : \"false\", \"link\" : \"\"}'>\n                                        <img src=\"https://isuhani-clinic-data.s3.ap-northeast-2.amazonaws.com/images/legacy/d721f1ec30328972.png\" data-lazy-src=\"https://isuhani-clinic-data.s3.ap-northeast-2.amazonaws.com/images/legacy/d721f1ec30328972.png\" data-width=\"254\" data-height=\"50\" alt=\"\" class=\"se-image-resource\" />\n                                    </a>\n                                </div>\n                        </div>\n                    </div>\n                </div>\n                <div class=\"se-component se-text se-l-default\" id=\"SE-d2885d25-bead-4ad5-9a3d-a21af8f16ebc\">\n                    <div class=\"se-component-content\">\n                        <div class=\"se-section se-section-text se-l-default\">\n                            <div class=\"se-module se-module-text\">\n                                    <!-- SE-TEXT { --><p class=\"se-text-paragraph se-text-paragraph-align-center \" style=\"\" id=\"SE-77117A30-9BC5-4A77-8E90-4F2385BB7A57\"><span style=\"\" class=\"se-fs- se-ff-   \" id=\"SE-F33320F3-9025-40B1-906D-1FF7369C8095\"><b>​</b></span></p><!-- } SE-TEXT --><!-- SE-TEXT { --><p class=\"se-text-paragraph se-text-paragraph-align-center \" style=\"\" id=\"SE-d7f95e3d-8d0b-40e2-bf9c-3f0b97c3858a\"><span style=\"color:#000000;\" class=\"se-fs- se-ff-nanumbareunhipi   \" id=\"SE-D07684B9-0E8F-486F-A556-1670EFD7949C\"><b>이수한의원</b></span></p><!-- } SE-TEXT --><!-- SE-TEXT { --><p class=\"se-text-paragraph se-text-paragraph-align-center \" style=\"\" id=\"SE-091a1957-ec24-474e-af03-385dc971ec9b\"><span style=\"color:#000000;\" class=\"se-fs- se-ff-nanumbareunhipi se-weight-unset  \" id=\"SE-8292A800-9C87-420C-BEF4-E6EE58AE9AF2\">남성역 1번 출구 | 일요일 진료</span></p><!-- } SE-TEXT -->\n                            </div>\n                        </div>\n                    </div>\n                </div>                <div class=\"se-component se-horizontalLine se-l-line2\" id=\"SE-f5765a32-f5bd-42c1-bdf5-574b8f414268\">\n                    <div class=\"se-component-content\">\n                        <div class=\"se-section se-section-horizontalLine se-l-line2 se-section-align-center\">\n                            <div class=\"se-module se-module-horizontalLine\">\n                                <hr class=\"se-hr\" />\n                            </div>\n                        </div>\n                    </div>\n                </div>                <div class=\"se-component se-text se-l-default\" id=\"SE-c8b7bf24-9f79-47e8-aeb4-d5ad98dacbd1\">\n                    <div class=\"se-component-content\">\n                        <div class=\"se-section se-section-text se-l-default\">\n                            <div class=\"se-module se-module-text\">\n                                    <!-- SE-TEXT { --><p class=\"se-text-paragraph se-text-paragraph-align-center \" style=\"line-height:1.8;\" id=\"SE-ca6bfa61-ad04-4117-8edc-98cd8d2158eb\"><span style=\"color:#000000;\" class=\"se-fs-fs15 se-ff-system  se-style-unset \" id=\"SE-9926F331-FAB3-462A-B3F5-E026EE8EE276\"><b>생맥산이 뭘까?</b></span></p><!-- } SE-TEXT --><!-- SE-TEXT { --><p class=\"se-text-paragraph se-text-paragraph-align-center \" style=\"line-height:1.8;\" id=\"SE-97129bb2-391d-4232-bbfe-c13270a8ef6e\"><span style=\"color:#000000;\" class=\"se-fs-fs15 se-ff-system  se-style-unset \" id=\"SE-3646ECB3-5EDC-4944-AF13-39A2848CC63A\"><b>​</b></span></p><!-- } SE-TEXT --><!-- SE-TEXT { --><p class=\"se-text-paragraph se-text-paragraph-align-justify \" style=\"line-height:1.8;\" id=\"SE-f5149360-1780-4271-9669-733a4e50d46d\"><span style=\"color:#000000;\" class=\"se-fs-fs15 se-ff-system  se-style-unset \" id=\"SE-F4CAAB58-07E7-425E-B948-4DFBF570443F\">무더운 여름철, 더위로 힘들 때 음료처럼 복용할 수 있는 대표적인 보약이 생맥산입니다. </span><span style=\"color:#000000;background-color:#b0f1ff;\" class=\"se-fs-fs15 se-ff-system  se-style-unset \" id=\"SE-CBBC089D-DCF6-47A3-B47D-3DB398DDCEDB\">생맥산은 인삼, 맥문동, 오미자를 다려 만들어</span><span style=\"color:#000000;\" class=\"se-fs-fs15 se-ff-system  se-style-unset \" id=\"SE-ADE0288F-6947-4B21-952D-C42D74B6BE0B\">졌으며, 이 세 약재는 폐의 기운을 돕고 폐열을 식혀주며 폐의 진액을 보충하고 자양하는 작용을 합니다.</span></p><!-- } SE-TEXT --><!-- SE-TEXT { --><p class=\"se-text-paragraph se-text-paragraph-align-justify \" style=\"line-height:1.8;\" id=\"SE-B874A3CF-D447-45DA-B745-CA2CEE20FDDF\"><span style=\"color:#000000;\" class=\"se-fs-fs15 se-ff-system  se-style-unset \" id=\"SE-6305ED71-B893-40E1-BEAD-310CB48CC2E6\">​</span></p><!-- } SE-TEXT --><!-- SE-TEXT { --><p class=\"se-text-paragraph se-text-paragraph-align-justify \" style=\"line-height:1.8;\" id=\"SE-c79c9fb2-049f-4f97-bfc3-e7332eee3127\"><span style=\"color:#000000;\" class=\"se-fs-fs15 se-ff-system  se-style-unset \" id=\"SE-50CF93CD-2B25-4CA8-B0B4-E3584D707DA6\">중국 금나라 금원사대가 중 한 명인 이동원이 저술한 &#x27;내외상변혹론&#x27;에는, 우리 몸의 원기를 생하게 해주는 약이라고 서술했으며, &#x27;동의보감&#x27;에서는 &#x27;여름에 끓인 물 대신 마시거나 혹은 황기, 감초, 황백을 더해 마시면 기력이 용출하고 생생하게 된다&#x27;라고 서술했습니다. 그리고 조선왕조실록에 따르면 경옥고와 더불어 가장 많이 처방되는 한약이라고 합니다.</span></p><!-- } SE-TEXT --><!-- SE-TEXT { --><p class=\"se-text-paragraph se-text-paragraph-align-justify \" style=\"line-height:1.8;\" id=\"SE-D16B5B1D-6480-4703-8050-6029BE89B27C\"><span style=\"color:#000000;\" class=\"se-fs-fs15 se-ff-system  se-style-unset \" id=\"SE-D42474B4-3AD3-43FE-9F26-34CCCE88271A\">​</span></p><!-- } SE-TEXT -->\n                            </div>\n                        </div>\n                    </div>\n                </div>                <div class=\"se-component se-imageStrip se-imageStrip2 se-l-default\" id=\"SE-74eee9eb-d047-4b64-a40a-957a6c0ff1da\">\n                    <div class=\"se-component-content se-component-content-extend\">\n                        <div class=\"se-section se-section-imageStrip se-l-default\">\n                            <div class=\"se-imageStrip-container se-imageStrip-col-2\">\n                                <div class=\"se-module se-module-image\" style=\"width:50.0%;\">\n                                    <a href=\"#\" class=\"se-module-image-link __se_image_link __se_link\" style=\"\" onclick=\"return false;\" data-linktype=\"img\" data-linkdata='{\"id\" : \"SE-3bbf061f-2be0-4e83-8574-e6a3fcf82c42\", \"src\" : \"https://isuhani-clinic-data.s3.ap-northeast-2.amazonaws.com/images/legacy/08790c691a3151a2.jpg\", \"originalWidth\" : \"401\", \"originalHeight\" : \"401\", \"linkUse\" : \"false\", \"link\" : \"\"}'>\n                                        <img src=\"https://isuhani-clinic-data.s3.ap-northeast-2.amazonaws.com/images/legacy/08790c691a3151a2.jpg\" data-lazy-src=\"https://isuhani-clinic-data.s3.ap-northeast-2.amazonaws.com/images/legacy/08790c691a3151a2.jpg\" data-width=\"401\" data-height=\"401\" alt=\"\" class=\"se-image-resource\" />\n                                    </a>\n                                </div>\n                                <div class=\"se-module se-module-image\" style=\"width:50.0%;\">\n                                    <a href=\"#\" class=\"se-module-image-link __se_image_link __se_link\" style=\"\" onclick=\"return false;\" data-linktype=\"img\" data-linkdata='{\"id\" : \"SE-fc04b9e8-99dc-4aba-ac87-efcfbc3ddc2d\", \"src\" : \"https://isuhani-clinic-data.s3.ap-northeast-2.amazonaws.com/images/legacy/cdbbe3cd3894ff6e.jpg\", \"originalWidth\" : \"401\", \"originalHeight\" : \"401\", \"linkUse\" : \"false\", \"link\" : \"\"}'>\n                                        <img src=\"https://isuhani-clinic-data.s3.ap-northeast-2.amazonaws.com/images/legacy/cdbbe3cd3894ff6e.jpg\" data-lazy-src=\"https://isuhani-clinic-data.s3.ap-northeast-2.amazonaws.com/images/legacy/cdbbe3cd3894ff6e.jpg\" data-width=\"401\" data-height=\"401\" alt=\"\" class=\"se-image-resource\" />\n                                    </a>\n                                </div>\n                            </div>\n                            <div class=\"se-module se-module-text se-caption\"><p class=\"se-text-paragraph se-text-paragraph-align- \" style=\"\" id=\"SE-F7025082-82E5-4A4B-8095-27731BFCE68D\"><span style=\"\" class=\"se-fs- se-ff-   \" id=\"SE-E3BF310D-DA99-4EE5-A226-5AF37D19F08A\">생맥산을 제조하는 이수한의원의 탕제실</span></p></div>\n                        </div>\n                    </div>\n                </div>                <div class=\"se-component se-text se-l-default\" id=\"SE-d86690cf-3aca-4893-aa5b-6d12639b2d78\">\n                    <div class=\"se-component-content\">\n                        <div class=\"se-section se-section-text se-l-default\">\n                            <div class=\"se-module se-module-text\">\n                                    <!-- SE-TEXT { --><p class=\"se-text-paragraph se-text-paragraph-align-center \" style=\"\" id=\"SE-3D7C0DEF-1974-429C-A872-AC48D780267E\"><span style=\"\" class=\"se-fs- se-ff-   \" id=\"SE-FAAB688F-A93C-45DE-B930-29554D89C43F\">​</span></p><!-- } SE-TEXT --><!-- SE-TEXT { --><p class=\"se-text-paragraph se-text-paragraph-align-center \" style=\"\" id=\"SE-F5057A3C-8ADE-46EC-875E-008C50B24239\"><span style=\"\" class=\"se-fs- se-ff-   \" id=\"SE-FEA2DC85-747E-4A11-8781-21AE5007655A\">​</span></p><!-- } SE-TEXT -->\n                            </div>\n                        </div>\n                    </div>\n                </div>                <div class=\"se-component se-horizontalLine se-l-line2\" id=\"SE-d11f25ef-8123-4e46-8274-9c309a5fb43f\">\n                    <div class=\"se-component-content\">\n                        <div class=\"se-section se-section-horizontalLine se-l-line2 se-section-align-center\">\n                            <div class=\"se-module se-module-horizontalLine\">\n                                <hr class=\"se-hr\" />\n                            </div>\n                        </div>\n                    </div>\n                </div>                <div class=\"se-component se-text se-l-default\" id=\"SE-570df9bf-63f7-4581-ab5e-373c4b1415e8\">\n                    <div class=\"se-component-content\">\n                        <div class=\"se-section se-section-text se-l-default\">\n                            <div class=\"se-module se-module-text\">\n                                    <!-- SE-TEXT { --><p class=\"se-text-paragraph se-text-paragraph-align-center \" style=\"line-height:1.8;\" id=\"SE-38b99965-408b-4d17-b863-65fa51b77d9c\"><span style=\"color:#000000;\" class=\"se-fs-fs15 se-ff-system  se-style-unset \" id=\"SE-86A10248-28D5-45AD-8005-D9BC28EA2E19\"><b>생맥산의 효능</b></span></p><!-- } SE-TEXT --><!-- SE-TEXT { --><p class=\"se-text-paragraph se-text-paragraph-align-center \" style=\"line-height:1.8;\" id=\"SE-05d4e313-8d33-4d09-9965-28a392b4a1bf\"><span style=\"color:#000000;\" class=\"se-fs-fs15 se-ff-system  se-style-unset \" id=\"SE-A1502FC4-E50D-437E-AC93-04584A9B602D\">​</span></p><!-- } SE-TEXT --><!-- SE-TEXT { --><p class=\"se-text-paragraph se-text-paragraph-align-justify \" style=\"line-height:1.8;\" id=\"SE-64c9db1c-7fd9-4f60-8016-84d4e73f93de\"><span style=\"color:#000000;\" class=\"se-fs-fs15 se-ff-system  se-style-unset \" id=\"SE-B50BE594-C1E7-4AD3-8A96-939F105919FD\">생맥산은 폐의 기능이 온전할 수 있는데 도움이 됩니다. 폐는 호흡을 주관하며 혈액 순환과 체액 대사를 조절하는 기능이 있는데, 열에 노출될수록 쉽게 고갈됩니다. 이럴 때 복용하게 되면 인삼이 폐의 기를 보해주며, 맥문동이 음을 기르고 진액을 공급하며, 오미자가 진액을 수렴시켜 기운이 흩어지지 않게 해줍니다. 그 결과, 기와 진액이 회복되고 원기가 다시 충만해집니다.</span></p><!-- } SE-TEXT --><!-- SE-TEXT { --><p class=\"se-text-paragraph se-text-paragraph-align-center \" style=\"\" id=\"SE-A2BF228A-F008-4921-989A-26B1E8BD0F44\"><span style=\"\" class=\"se-fs- se-ff-   \" id=\"SE-F0C3A1D6-C384-4E30-9C4A-791DDD6BF3C8\">​</span></p><!-- } SE-TEXT -->\n                            </div>\n                        </div>\n                    </div>\n                </div>                <div class=\"se-component se-image se-l-default\" id=\"SE-4ccf276a-eee4-4fb3-9cec-14b5f73f5402\">\n                    <div class=\"se-component-content se-component-content-normal\">\n                        <div class=\"se-section se-section-image se-l-default se-section-align-center\" style=\"max-width:401px;\">\n                                <div class=\"se-module se-module-image\" style=\"\">\n                                    <a href=\"#\" class=\"se-module-image-link __se_image_link __se_link\" style=\"\" onclick=\"return false;\" data-linktype=\"img\" data-linkdata='{\"id\" : \"SE-4ccf276a-eee4-4fb3-9cec-14b5f73f5402\", \"src\" : \"https://isuhani-clinic-data.s3.ap-northeast-2.amazonaws.com/images/legacy/9831ec8d9561670e.jpg\", \"originalWidth\" : \"401\", \"originalHeight\" : \"401\", \"linkUse\" : \"false\", \"link\" : \"\"}'>\n                                        <img src=\"https://isuhani-clinic-data.s3.ap-northeast-2.amazonaws.com/images/legacy/9831ec8d9561670e.jpg\" data-lazy-src=\"https://isuhani-clinic-data.s3.ap-northeast-2.amazonaws.com/images/legacy/9831ec8d9561670e.jpg\" data-width=\"401\" data-height=\"401\" alt=\"\" class=\"se-image-resource\" />\n                                    </a>\n                                </div>\n                            <div class=\"se-module se-module-text se-caption\"><p class=\"se-text-paragraph se-text-paragraph-align- \" style=\"\" id=\"SE-6AA1735D-F90D-40E9-A3CB-B7F2ED0E8A6C\"><span style=\"\" class=\"se-fs- se-ff-   \" id=\"SE-4F2B6505-F51B-4C2F-A9B5-18E30D7BDF81\">생맥산의 효능을 설명하시는 문학진 원장님</span></p></div>\n                        </div>\n                    </div>\n                </div>\n                <div class=\"se-component se-text se-l-default\" id=\"SE-a4c24625-5ca3-46fe-91e9-572e9ee4cff0\">\n                    <div class=\"se-component-content\">\n                        <div class=\"se-section se-section-text se-l-default\">\n                            <div class=\"se-module se-module-text\">\n                                    <!-- SE-TEXT { --><p class=\"se-text-paragraph se-text-paragraph-align-center \" style=\"\" id=\"SE-78F75F61-87B8-4D14-9FCF-96217F5EA714\"><span style=\"\" class=\"se-fs- se-ff-   \" id=\"SE-42FAB9B8-2466-452B-BB88-A5A0AED63433\">​</span></p><!-- } SE-TEXT --><!-- SE-TEXT { --><p class=\"se-text-paragraph se-text-paragraph-align-center \" style=\"\" id=\"SE-0E679DFA-EB33-47D3-8707-B094238894C3\"><span style=\"\" class=\"se-fs- se-ff-   \" id=\"SE-9DB4DB3F-2F40-43D1-A751-D1EE5378B97A\">​</span></p><!-- } SE-TEXT --><!-- SE-TEXT { --><p class=\"se-text-paragraph se-text-paragraph-align-center \" style=\"\" id=\"SE-69A073C7-641B-4476-BF99-1664AE5F741A\"><span style=\"\" class=\"se-fs- se-ff-   \" id=\"SE-10466981-DF46-4D9A-82DD-B8F09919541C\">​</span></p><!-- } SE-TEXT -->\n                            </div>\n                        </div>\n                    </div>\n                </div>                <div class=\"se-component se-horizontalLine se-l-line2\" id=\"SE-c780fe20-e698-4c34-bfa5-b1b6b42ececa\">\n                    <div class=\"se-component-content\">\n                        <div class=\"se-section se-section-horizontalLine se-l-line2 se-section-align-center\">\n                            <div class=\"se-module se-module-horizontalLine\">\n                                <hr class=\"se-hr\" />\n                            </div>\n                        </div>\n                    </div>\n                </div>                <div class=\"se-component se-text se-l-default\" id=\"SE-35c9f9eb-b5e0-4b9a-ac4c-0f389394650c\">\n                    <div class=\"se-component-content\">\n                        <div class=\"se-section se-section-text se-l-default\">\n                            <div class=\"se-module se-module-text\">\n                                    <!-- SE-TEXT { --><p class=\"se-text-paragraph se-text-paragraph-align-center \" style=\"line-height:1.8;\" id=\"SE-d62ba050-e4eb-4b89-b8d3-870aed041b14\"><span style=\"color:#000000;\" class=\"se-fs-fs15 se-ff-system  se-style-unset \" id=\"SE-76FD0E03-4446-4BED-ABC4-0EEF35E6F28B\"><b>어린이에게도 좋은, &#x27;생맥산&#x27;</b></span></p><!-- } SE-TEXT --><!-- SE-TEXT { --><p class=\"se-text-paragraph se-text-paragraph-align-center \" style=\"line-height:1.8;\" id=\"SE-d5ea6219-42c9-417a-8b6c-f7310ba0972b\"><span style=\"color:#000000;\" class=\"se-fs-fs15 se-ff-system  se-style-unset \" id=\"SE-8F60B4BF-5969-429C-B53B-715FC9C822E2\">​</span></p><!-- } SE-TEXT --><!-- SE-TEXT { --><p class=\"se-text-paragraph se-text-paragraph-align-justify \" style=\"line-height:1.8;\" id=\"SE-e46f05fd-eea1-4c8b-a44c-0c631c000adc\"><span style=\"color:#000000;\" class=\"se-fs-fs15 se-ff-system  se-style-unset \" id=\"SE-0064543A-07A2-49FC-B819-78BB191EEC2C\">어린이들은 체질적으로 성인에 비해 열이 많습니다. 땀도 쉽게 많이 흘리기 때문에 여름이 되면 체력이 쉽게 떨어지기 마련입니다. 이때 찬 음료나 음식을 과다하게 섭취하게 되면 소화기에 문제가 생기게 됩니다. 특히 환절기에 호흡기 면역력이 약해져 힘들었던 경우하면 더욱 여름철 건강관리에 신경을 써야 합니다. 특히, 어린이에게 주하병이 발생하게 되면 머리가 아프며 다리에 힘이 없으며 식사량이 적어지고 몸에서 열이 나는 증세를 보이게 됩니다. </span></p><!-- } SE-TEXT --><!-- SE-TEXT { --><p class=\"se-text-paragraph se-text-paragraph-align-justify \" style=\"line-height:1.8;\" id=\"SE-4DEC351E-5DD9-4D80-AC64-563AE8861DED\"><span style=\"color:#000000;\" class=\"se-fs-fs15 se-ff-system  se-style-unset \" id=\"SE-EC9A0D88-4D66-4394-AA57-4D3F72846703\">​</span></p><!-- } SE-TEXT --><!-- SE-TEXT { --><p class=\"se-text-paragraph se-text-paragraph-align-justify \" style=\"line-height:1.8;\" id=\"SE-b6d2a54d-d94a-41fc-96e9-d7bf3c45d64b\"><span style=\"color:#000000;\" class=\"se-fs-fs15 se-ff-system  se-style-unset \" id=\"SE-78ACC054-7181-4F46-A368-8BDB666D4A2D\">이때 생맥산을 복용하게 되면 부족했던 원기를 채울 수 있으며, 습열로 인한 증상들을 완화시킬 수 있습니다.</span></p><!-- } SE-TEXT --><!-- SE-TEXT { --><p class=\"se-text-paragraph se-text-paragraph-align-justify \" style=\"line-height:1.8;\" id=\"SE-CC0EBB9C-B364-4317-8F15-AC3BEC8E9C44\"><span style=\"color:#000000;\" class=\"se-fs-fs15 se-ff-system  se-style-unset \" id=\"SE-2660098C-D17B-493B-A40E-2DC56B9807FD\">​</span></p><!-- } SE-TEXT -->\n                            </div>\n                        </div>\n                    </div>\n                </div>                <div class=\"se-component se-image se-l-default\" id=\"SE-5aba6b21-5f83-4636-b3c8-ebcd59286da4\">\n                    <div class=\"se-component-content se-component-content-normal\">\n                        <div class=\"se-section se-section-image se-l-default se-section-align-center\" style=\"max-width:401px;\">\n                                <div class=\"se-module se-module-image\" style=\"\">\n                                    <a href=\"#\" class=\"se-module-image-link __se_image_link __se_link\" style=\"\" onclick=\"return false;\" data-linktype=\"img\" data-linkdata='{\"id\" : \"SE-5aba6b21-5f83-4636-b3c8-ebcd59286da4\", \"src\" : \"https://isuhani-clinic-data.s3.ap-northeast-2.amazonaws.com/images/legacy/d2ae9d628ad4d931.jpg\", \"originalWidth\" : \"401\", \"originalHeight\" : \"401\", \"linkUse\" : \"false\", \"link\" : \"\"}'>\n                                        <img src=\"https://isuhani-clinic-data.s3.ap-northeast-2.amazonaws.com/images/legacy/d2ae9d628ad4d931.jpg\" data-lazy-src=\"https://isuhani-clinic-data.s3.ap-northeast-2.amazonaws.com/images/legacy/d2ae9d628ad4d931.jpg\" data-width=\"401\" data-height=\"401\" alt=\"\" class=\"se-image-resource\" />\n                                    </a>\n                                </div>\n                            <div class=\"se-module se-module-text se-caption\"><p class=\"se-text-paragraph se-text-paragraph-align- \" style=\"\" id=\"SE-477ECC17-48B3-4E96-B8CD-23674866CA0E\"><span style=\"\" class=\"se-fs- se-ff-   \" id=\"SE-9CF0B974-E348-4661-AF70-F48772D91676\">땀을 많이 흘리는 어린이들</span></p></div>\n                        </div>\n                    </div>\n                </div>\n                <div class=\"se-component se-text se-l-default\" id=\"SE-41bb65e4-2ff5-41b3-8ef8-c1f01cef0074\">\n                    <div class=\"se-component-content\">\n                        <div class=\"se-section se-section-text se-l-default\">\n                            <div class=\"se-module se-module-text\">\n                                    <!-- SE-TEXT { --><p class=\"se-text-paragraph se-text-paragraph-align-center \" style=\"\" id=\"SE-9e9ee07d-be07-4156-a3ec-23570a28b2bd\"><span style=\"\" class=\"se-fs- se-ff-   \" id=\"SE-D1C478F2-8185-432D-A1E5-3E7247955A21\"> </span></p><!-- } SE-TEXT --><!-- SE-TEXT { --><p class=\"se-text-paragraph se-text-paragraph-align-center \" style=\"\" id=\"SE-A7F93F79-25FD-4252-833D-AE3E317C13E3\"><span style=\"\" class=\"se-fs- se-ff-   \" id=\"SE-DD05EA65-44B1-45AE-B886-33C617D01A35\">​</span></p><!-- } SE-TEXT --><!-- SE-TEXT { --><p class=\"se-text-paragraph se-text-paragraph-align-center \" style=\"\" id=\"SE-B9284243-80A6-470F-82E5-05AD86731E69\"><span style=\"\" class=\"se-fs- se-ff-   \" id=\"SE-45AF602C-9DD4-428D-ABC3-F2603F6C651D\">​</span></p><!-- } SE-TEXT -->\n                            </div>\n                        </div>\n                    </div>\n                </div>                <div class=\"se-component se-horizontalLine se-l-line2\" id=\"SE-96508720-5d43-499c-882a-b4c3d2b42d04\">\n                    <div class=\"se-component-content\">\n                        <div class=\"se-section se-section-horizontalLine se-l-line2 se-section-align-center\">\n                            <div class=\"se-module se-module-horizontalLine\">\n                                <hr class=\"se-hr\" />\n                            </div>\n                        </div>\n                    </div>\n                </div>                <div class=\"se-component se-text se-l-default\" id=\"SE-fd6f9b41-2be1-4ce6-8a30-c59915ca9aad\">\n                    <div class=\"se-component-content\">\n                        <div class=\"se-section se-section-text se-l-default\">\n                            <div class=\"se-module se-module-text\">\n                                    <!-- SE-TEXT { --><p class=\"se-text-paragraph se-text-paragraph-align-center \" style=\"line-height:1.8;\" id=\"SE-b1a593a4-22e8-43b7-a3d0-7e1dbe90087a\"><span style=\"color:#000000;\" class=\"se-fs-fs15 se-ff-system  se-style-unset \" id=\"SE-95E227EC-8BD2-471E-805B-C5642AB23C68\"><b>다양한 생맥산 음용법</b></span></p><!-- } SE-TEXT --><!-- SE-TEXT { --><p class=\"se-text-paragraph se-text-paragraph-align-center \" style=\"line-height:1.8;\" id=\"SE-f03047c0-03f5-4d99-ba83-61e018b98a41\"><span style=\"color:#000000;\" class=\"se-fs-fs15 se-ff-system  se-style-unset \" id=\"SE-1A0EC52E-4567-4A9C-AE4D-ABDD76254DAC\">​</span></p><!-- } SE-TEXT --><!-- SE-TEXT { --><p class=\"se-text-paragraph se-text-paragraph-align-justify \" style=\"line-height:1.8;\" id=\"SE-a4e13b23-2f4e-4440-90a6-97fae7ecef5e\"><span style=\"color:#000000;\" class=\"se-fs-fs15 se-ff-system  se-style-unset \" id=\"SE-D599C5CA-4B88-47DE-8996-E868E38CA9F9\">생맥산은 단독으로 처방되기도 하지만, 병증에 따라 합방하여 사용되기도 합니다. 생맥산에 더하여 음용할 수 있는 한약 몇가지를 알려드리겠습니다. </span></p><!-- } SE-TEXT --><!-- SE-TEXT { --><p class=\"se-text-paragraph se-text-paragraph-align-justify \" style=\"line-height:1.8;\" id=\"SE-dcca1d81-427a-4d21-b44b-8880eb775bf6\"><span style=\"color:#000000;\" class=\"se-fs-fs15 se-ff-system  se-style-unset \" id=\"SE-c8662b65-9f38-4e5b-a145-ffca56e5103a\">​</span></p><!-- } SE-TEXT --><!-- SE-TEXT { --><p class=\"se-text-paragraph se-text-paragraph-align-justify \" style=\"line-height:1.8;\" id=\"SE-df67fb4e-868c-455f-bfc5-11fe068f80f2\"><span style=\"color:#000000;background-color:#b0f1ff;\" class=\"se-fs-fs15 se-ff-system  se-style-unset \" id=\"SE-f198a267-30ec-4143-a16c-69dd7422b473\">보증익기탕</span></p><!-- } SE-TEXT --><!-- SE-TEXT { --><p class=\"se-text-paragraph se-text-paragraph-align-justify \" style=\"line-height:1.8;\" id=\"SE-d288b76d-1931-4e61-a542-4e85f30eb7cb\"><span style=\"color:#000000;\" class=\"se-fs-fs15 se-ff-system  se-style-unset \" id=\"SE-305228f6-e5ff-4726-a732-a53a641df409\">황기, 인삼, 백출, 감초, 당귀신, 진피, 승마, 시호로 구성되어있는 탕약으로, 병후의 피로, 기가 허한증상, 식욕부진 개선 등의 체력증강제로 처방됩니다.</span></p><!-- } SE-TEXT --><!-- SE-TEXT { --><p class=\"se-text-paragraph se-text-paragraph-align-justify \" style=\"line-height:1.8;\" id=\"SE-25b6fee1-7573-4724-92fe-25cec71f742f\"><span style=\"color:#000000;\" class=\"se-fs-fs15 se-ff-system  se-style-unset \" id=\"SE-78c0477a-638c-4562-9156-88a01877903e\">​</span></p><!-- } SE-TEXT --><!-- SE-TEXT { --><p class=\"se-text-paragraph se-text-paragraph-align-justify \" style=\"line-height:1.8;\" id=\"SE-03715c37-bc06-4fb7-93ff-0d416c638e9a\"><span style=\"color:#000000;background-color:#b0f1ff;\" class=\"se-fs-fs15 se-ff-system  se-style-unset \" id=\"SE-1c2338c0-9931-494e-ad26-438bd4a4a7e7\">사물탕</span></p><!-- } SE-TEXT --><!-- SE-TEXT { --><p class=\"se-text-paragraph se-text-paragraph-align-justify \" style=\"line-height:1.8;\" id=\"SE-a08fb2be-41fd-4414-b259-c38814c98a8f\"><span style=\"color:#000000;\" class=\"se-fs-fs15 se-ff-system  se-style-unset \" id=\"SE-c0f22ed0-8102-4269-a417-32c0d9d6023e\">당귀, 천궁, 백작약, 숙지황으로 구성되어있는 탕약이며, 모든 혈병 및 월경 관련 증상에 처방됩니다. 여기에 인삼, 백출, 백복령, 감초를 보태면 기와 혈을 보해주는 팔진탕이 되고, 황금, 황백, 감초를 보태면 음허조열을 치료하는 삼황사물탕이 됩니다. </span></p><!-- } SE-TEXT --><!-- SE-TEXT { --><p class=\"se-text-paragraph se-text-paragraph-align-justify \" style=\"line-height:1.8;\" id=\"SE-8d6b45be-f614-45c9-a57c-fb17585597d1\"><span style=\"color:#000000;\" class=\"se-fs-fs15 se-ff-system  se-style-unset \" id=\"SE-161099ad-70de-447a-90a1-4605d6c80e5e\">​</span></p><!-- } SE-TEXT --><!-- SE-TEXT { --><p class=\"se-text-paragraph se-text-paragraph-align-justify \" style=\"line-height:1.8;\" id=\"SE-ef0dd5b4-0f4d-49d5-b16c-bb722d5b8e22\"><span style=\"color:#000000;background-color:#bdfbfa;\" class=\"se-fs-fs15 se-ff-system  se-style-unset \" id=\"SE-f07ed543-262d-4de6-8d41-cfdaba2d2f28\">팔물탕</span></p><!-- } SE-TEXT --><!-- SE-TEXT { --><p class=\"se-text-paragraph se-text-paragraph-align-justify \" style=\"line-height:1.8;\" id=\"SE-f9599238-b6ad-475b-b41f-dcd468025b16\"><span style=\"color:#000000;\" class=\"se-fs-fs15 se-ff-system  se-style-unset \" id=\"SE-9f582894-e6c8-42a3-85d3-c6811de91501\">인삼, 황기, 향부자, 당귀, 천궁, 백출, 백작약, 대추, 약쑥으로 구성되어있는 탕약이며,</span></p><!-- } SE-TEXT --><!-- SE-TEXT { --><p class=\"se-text-paragraph se-text-paragraph-align-justify \" style=\"line-height:1.8;\" id=\"SE-9e6c7801-5860-4e6a-b3da-1ab7749f9c76\"><span style=\"color:#000000;\" class=\"se-fs-fs15 se-ff-system  se-style-unset \" id=\"SE-72e7723a-b8c5-4575-8b37-154b7c7f17fd\">허로증(전신이 허약하여 뼈마디가 쑤시고 아프며, 가끔 열이 오르고 허리가 아프며 잠을 자면 땀이나는 증상. 놀란 사람 같이 가슴이 뛰고 불안초조하며 기운이 없어 눕고만 싶어짐.) 및 소음인 체질에 탁월한 효과를 보입니다. </span></p><!-- } SE-TEXT --><!-- SE-TEXT { --><p class=\"se-text-paragraph se-text-paragraph-align-justify \" style=\"line-height:1.8;\" id=\"SE-12020f58-d275-47fa-83e9-9c10d006a88e\"><span style=\"color:#000000;\" class=\"se-fs-fs15 se-ff-system  se-style-unset \" id=\"SE-5f0daa18-813b-41f4-a211-7eeb891a55ba\">​</span></p><!-- } SE-TEXT --><!-- SE-TEXT { --><p class=\"se-text-paragraph se-text-paragraph-align-justify \" style=\"line-height:1.8;\" id=\"SE-b4ad60fe-38a5-4fe4-b41f-62e94b89e011\"><span style=\"color:#000000;\" class=\"se-fs-fs15 se-ff-system  se-style-unset \" id=\"SE-599b8cd6-94fc-4256-ac98-d645de9691ac\">이외에도 오미자청이나 꿀을 조금 첨가하여 마시면 더욱 좋습니다.</span></p><!-- } SE-TEXT --><!-- SE-TEXT { --><p class=\"se-text-paragraph se-text-paragraph-align-center \" style=\"\" id=\"SE-EEE55814-331E-4788-B689-851C6BD10441\"><span style=\"\" class=\"se-fs- se-ff-   \" id=\"SE-BE087BB3-05B3-485B-8744-04A8A9982C5B\">​</span></p><!-- } SE-TEXT -->\n                            </div>\n                        </div>\n                    </div>\n                </div>                <div class=\"se-component se-image se-l-default\" id=\"SE-b075f52b-ec31-4735-b7f6-9ee124dcd76e\">\n                    <div class=\"se-component-content se-component-content-normal\">\n                        <div class=\"se-section se-section-image se-l-default se-section-align-center\" style=\"max-width:401px;\">\n                                <div class=\"se-module se-module-image\" style=\"\">\n                                    <a href=\"#\" class=\"se-module-image-link __se_image_link __se_link\" style=\"\" onclick=\"return false;\" data-linktype=\"img\" data-linkdata='{\"id\" : \"SE-b075f52b-ec31-4735-b7f6-9ee124dcd76e\", \"src\" : \"https://isuhani-clinic-data.s3.ap-northeast-2.amazonaws.com/images/legacy/7ca8823f4d49184e.jpg\", \"originalWidth\" : \"401\", \"originalHeight\" : \"401\", \"linkUse\" : \"false\", \"link\" : \"\"}'>\n                                        <img src=\"https://isuhani-clinic-data.s3.ap-northeast-2.amazonaws.com/images/legacy/7ca8823f4d49184e.jpg\" data-lazy-src=\"https://isuhani-clinic-data.s3.ap-northeast-2.amazonaws.com/images/legacy/7ca8823f4d49184e.jpg\" data-width=\"401\" data-height=\"401\" alt=\"\" class=\"se-image-resource\" />\n                                    </a>\n                                </div>\n                            <div class=\"se-module se-module-text se-caption\"><p class=\"se-text-paragraph se-text-paragraph-align- \" style=\"\" id=\"SE-6913567F-DAD5-4AC5-AC43-2F618BA585EA\"><span style=\"\" class=\"se-fs- se-ff-   \" id=\"SE-9B871F95-4815-4B5B-88E6-896651AFAA58\">생맥산 처방은, 이수한의원!</span></p></div>\n                        </div>\n                    </div>\n                </div>\n                <div class=\"se-component se-text se-l-default\" id=\"SE-801cf6bb-ba50-42a5-ace0-cd68917293a3\">\n                    <div class=\"se-component-content\">\n                        <div class=\"se-section se-section-text se-l-default\">\n                            <div class=\"se-module se-module-text\">\n                                    <!-- SE-TEXT { --><p class=\"se-text-paragraph se-text-paragraph-align-center \" style=\"\" id=\"SE-85f43f28-5ea0-4185-8e4b-571afa309025\"><span style=\"\" class=\"se-fs- se-ff-   \" id=\"SE-72bed2cf-61fa-4751-81ff-da8ac43a8f8e\"> </span></p><!-- } SE-TEXT --><!-- SE-TEXT { --><p class=\"se-text-paragraph se-text-paragraph-align-center \" style=\"\" id=\"SE-c416bab6-8035-49c1-bc3e-2ef0e99ff7b6\"><span style=\"\" class=\"se-fs- se-ff-   \" id=\"SE-4871cd80-0099-40c9-8a9f-5b99a72a2c4d\">​</span></p><!-- } SE-TEXT --><!-- SE-TEXT { --><p class=\"se-text-paragraph se-text-paragraph-align-center \" style=\"\" id=\"SE-587a9707-9bf9-4625-92d8-a4ce89626c79\"><span style=\"\" class=\"se-fs- se-ff-   \" id=\"SE-f9f67190-0897-4de2-82ae-23c464cd9e5a\">​</span></p><!-- } SE-TEXT -->\n                            </div>\n                        </div>\n                    </div>\n                </div>                <div class=\"se-component se-horizontalLine se-l-line2\" id=\"SE-63077056-349d-4408-8586-f190b5c41bce\">\n                    <div class=\"se-component-content\">\n                        <div class=\"se-section se-section-horizontalLine se-l-line2 se-section-align-center\">\n                            <div class=\"se-module se-module-horizontalLine\">\n                                <hr class=\"se-hr\" />\n                            </div>\n                        </div>\n                    </div>\n                </div>                <div class=\"se-component se-text se-l-default\" id=\"SE-5e633e22-6b7c-45ee-abee-6cc08d76841e\">\n                    <div class=\"se-component-content\">\n                        <div class=\"se-section se-section-text se-l-default\">\n                            <div class=\"se-module se-module-text\">\n                                    <!-- SE-TEXT { --><p class=\"se-text-paragraph se-text-paragraph-align-center \" style=\"line-height:1.8;\" id=\"SE-17bc76ef-6d78-4861-86b0-f0147e643f82\"><span style=\"color:#000000;\" class=\"se-fs-fs15 se-ff-system  se-style-unset \" id=\"SE-13b112e7-16e4-4f99-bfc8-54d51ce65443\"><b>생맥산 관련 주의사항</b></span></p><!-- } SE-TEXT --><!-- SE-TEXT { --><p class=\"se-text-paragraph se-text-paragraph-align-center \" style=\"line-height:1.8;\" id=\"SE-3421a547-6e08-4d93-9429-53796bcaf062\"><span style=\"color:#000000;\" class=\"se-fs-fs15 se-ff-system  se-style-unset \" id=\"SE-0cdeb5e4-73b6-4c9e-aef7-e62e2b120d25\">​</span></p><!-- } SE-TEXT --><!-- SE-TEXT { --><p class=\"se-text-paragraph se-text-paragraph-align-justify \" style=\"line-height:1.8;\" id=\"SE-97e703b8-1b24-4854-b4ea-ca5015b7a88f\"><span style=\"color:#000000;\" class=\"se-fs-fs15 se-ff-system  se-style-unset \" id=\"SE-378a3d67-c08f-4477-b223-3cb000de02d4\">생맥산과 관련한 몇가지 주의사항이 있습니다. </span><span style=\"color:#000000;\" class=\"se-fs- se-ff-system  se-style-unset \" id=\"SE-4127c496-def6-4a0c-a965-36d1672fd721\">우선 첫번째로, 다른 약물을 투여 받고 있는 환자, 생리 기능이 저하 되어있는 고령자의 경우엔 복용전 반드시 전문의의 처방을 받아야합니다. 두번째, 생맥산 복용 후 발진 및 두드러기가 있거나 혹은 증상의 개선이 없을 경우 복용을 즉각 중지하고 전문의를 찾으시길 바랍니다. 세번째, 정해진 용법과 용량을 잘지켜서 복용해야하며, 다른 한약제제등과 함께 복용할 경우에는 함유 생약의 중복에 주의해야합니다. 마지막으로 네번째, 보관시직사광선을 피하고 되도록 습기가 적은 서늘한 곳에 보관해야하며, 실온보관(1-30℃)을 해야합니다.</span></p><!-- } SE-TEXT --><!-- SE-TEXT { --><p class=\"se-text-paragraph se-text-paragraph-align-justify \" style=\"line-height:1.8;\" id=\"SE-63755782-4805-4b20-804f-160bd6e8bc40\"><span style=\"color:#000000;\" class=\"se-fs-fs15 se-ff-system  se-style-unset \" id=\"SE-a5ead716-a228-45f7-a4e5-bb35c429478f\">​</span></p><!-- } SE-TEXT --><!-- SE-TEXT { --><p class=\"se-text-paragraph se-text-paragraph-align-center \" style=\"\" id=\"SE-BAFFC19A-9AD0-4376-9D2B-859AEFB10BEB\"><span style=\"\" class=\"se-fs- se-ff-   \" id=\"SE-31780BBD-34BF-44AF-800D-877A44B2C44F\">​</span></p><!-- } SE-TEXT -->\n                            </div>\n                        </div>\n                    </div>\n                </div>                <div class=\"se-component se-horizontalLine se-l-line6\" id=\"SE-ebca1a17-7f11-4e5e-a3a9-d43f60d3c36b\">\n                    <div class=\"se-component-content\">\n                        <div class=\"se-section se-section-horizontalLine se-l-line6 se-section-align-center\">\n                            <div class=\"se-module se-module-horizontalLine\">\n                                <hr class=\"se-hr\" />\n                            </div>\n                        </div>\n                    </div>\n                </div>                <div class=\"se-component se-text se-l-default\" id=\"SE-bddaf49d-6268-4ffa-9fe0-a95829b67c05\">\n                    <div class=\"se-component-content\">\n                        <div class=\"se-section se-section-text se-l-default\">\n                            <div class=\"se-module se-module-text\">\n                                    <!-- SE-TEXT { --><p class=\"se-text-paragraph se-text-paragraph-align-center \" style=\"\" id=\"SE-BCDCCD30-4657-4850-BFBD-30225CBBFCCF\"><span style=\"\" class=\"se-fs- se-ff-   \" id=\"SE-C5D25981-75A2-4F75-8607-F78689ACBD14\">​</span></p><!-- } SE-TEXT --><!-- SE-TEXT { --><p class=\"se-text-paragraph se-text-paragraph-align-justify \" style=\"\" id=\"SE-66c6bc65-67dd-4e60-9d42-489336717fea\"><span style=\"color:#000000;background-color:#ffffff;\" class=\"se-fs-fs15 se-ff-system  se-style-unset \" id=\"SE-FF73A925-84C0-49A5-8C70-FB0B1BE4B388\">저희 이수 한의원에서는 하루 1팩을 기준으로, 한  달 분인 30팩을 단위로 처방하고 있습니다. 필요시 수시 복용으로 더 추가를 하기도 하며, 체질 및 증상에 따라 다양하게 처방이 이루어지므로, 내원하셔서 진료를 받아보시길 바랍니다.</span></p><!-- } SE-TEXT --><!-- SE-TEXT { --><p class=\"se-text-paragraph se-text-paragraph-align-justify \" style=\"\" id=\"SE-CB28E675-DFD4-4F05-92A0-DB9B52DC9BBE\"><span style=\"color:#000000;\" class=\"se-fs-fs15 se-ff-system  se-style-unset \" id=\"SE-BA5C15ED-3E98-4023-8155-9A3F2FC09538\">​</span></p><!-- } SE-TEXT -->\n                            </div>\n                        </div>\n                    </div>\n                </div>                <div class=\"se-component se-oglink se-l-moment\" id=\"SE-D2775A87-FC12-46E5-B21B-ADF6C72438E4\">\n                    <div class=\"se-component-content\">\n                        <div class=\"se-section se-section-oglink se-l-moment se-section-align-center\">\n                            <div class=\"se-module se-module-oglink\">\n                                <a href=\"https://m.blog.naver.com/metroparis/moment/3198836\" class=\"se-oglink-thumbnail\" target=\"_blank\">\n                                    <img src=\"https://isuhani-clinic-data.s3.ap-northeast-2.amazonaws.com/images/legacy/a6ee0bdf6a8a90dd.jpg\" class=\"se-oglink-thumbnail-resource\" alt=\"\" />\n                                    <span class=\"se-oglink-thumbnail-moment-icon\"></span>\n                                </a>\n                                <a href=\"https://m.blog.naver.com/metroparis/moment/3198836\" class=\"se-oglink-info\" target=\"_blank\">\n                                    <div class=\"se-oglink-info-container\">\n                                        <strong class=\"se-oglink-title\">#생맥산 #여름한약 #여름보약 #이수한의원 #이수생맥산 #남성역생맥산 #어린이한약 #지금여기\n\n무더운 여름철, 이수한의원에서 제조한 생맥산을 드셔보세요👍</strong>\n                                        <p class=\"se-oglink-summary\"></p>\n                                        <p class=\"se-oglink-url\">m.blog.naver.com</p>\n                                    </div>\n                                </a>\n                            </div>\n                        </div>\n                    </div>\n                    <script type=\"text/data\" class=\"__se_module_data\" data-module='{\"type\":\"v2_oglink\", \"id\" :\"SE-D2775A87-FC12-46E5-B21B-ADF6C72438E4\", \"data\" : {\"link\" : \"https://m.blog.naver.com/metroparis/moment/3198836\", \"isVideo\" : \"false\", \"thumbnail\" : \"https://isuhani-clinic-data.s3.ap-northeast-2.amazonaws.com/images/legacy/a6ee0bdf6a8a90dd.jpg\"}}'></script>\n                </div>                <div class=\"se-component se-text se-l-default\" id=\"SE-D52145F0-E843-43D7-A203-3D76C90B64C5\">\n                    <div class=\"se-component-content\">\n                        <div class=\"se-section se-section-text se-l-default\">\n                            <div class=\"se-module se-module-text\">\n                                    <!-- SE-TEXT { --><p class=\"se-text-paragraph se-text-paragraph-align- \" style=\"\" id=\"SE-9371039C-6BEB-4423-8CA6-33284794EE13\"><span style=\"\" class=\"se-fs- se-ff-   \" id=\"SE-50976B8A-F571-4EE4-8A04-2AC0E64CF8BA\">​</span></p><!-- } SE-TEXT -->\n                            </div>\n                        </div>\n                    </div>\n                </div>                <div class=\"se-component se-horizontalLine se-l-line6\" id=\"SE-6855c164-9829-4901-bc55-fbcd9d04bcd5\">\n                    <div class=\"se-component-content\">\n                        <div class=\"se-section se-section-horizontalLine se-l-line6 se-section-align-center\">\n                            <div class=\"se-module se-module-horizontalLine\">\n                                <hr class=\"se-hr\" />\n                            </div>\n                        </div>\n                    </div>\n                </div>                <div class=\"se-component se-text se-l-default\" id=\"SE-7d413781-9c9e-4c20-88f9-2b97f5302ab8\">\n                    <div class=\"se-component-content\">\n                        <div class=\"se-section se-section-text se-l-default\">\n                            <div class=\"se-module se-module-text\">\n                                    <!-- SE-TEXT { --><p class=\"se-text-paragraph se-text-paragraph-align- \" style=\"\" id=\"SE-D5E70094-D7F4-40A8-A3A1-304689232F8D\"><span style=\"\" class=\"se-fs- se-ff-   \" id=\"SE-6D02F95C-49A8-48E5-8A22-C02AF783E7DF\">​</span></p><!-- } SE-TEXT -->\n                            </div>\n                        </div>\n                    </div>\n                </div>                <div class=\"se-component se-video se-l-default\">\n                    <div class=\"se-component-content se-component-content-fit\">\n                        <div class=\"se-section se-section-video se-section-align-center se-l-default\" >\n                            <div class=\"se-module se-module-video\" id=\"SE-b438a081-e16e-4bc8-bf2b-fe8a0a1db8bb\">\n                            </div>\n                        </div>\n                    </div>\n                    <script type=\"text/data\" class=\"__se_module_data\" data-module='{\"type\":\"v2_video\", \"id\" :\"SE-b438a081-e16e-4bc8-bf2b-fe8a0a1db8bb\", \"data\" : { \"videoType\" : \"player\", \"vid\" : \"F9C20AE733E2CB67AC39231E17F531B10E29\", \"inkey\" : \"V124b19f0181266d712a6094d0787416655bfa098bf2000769f37fa326952c1b7bdf6094d0787416655bf\", \"thumbnail\": \"https://isuhani-clinic-data.s3.ap-northeast-2.amazonaws.com/images/legacy/c9c3191abac6f074.jpg\", \"originalWidth\": \"608\", \"originalHeight\": \"1080\", \"width\": \"500\", \"height\": \"888\", \"contentMode\": \"fit\", \"format\": \"normal\", \"mediaMeta\": {\"@ctype\":\"mediaMeta\",\"title\":\"생맥산\",\"tags\":[\"이수생맥산\",\"생맥산\",\"이수여름한약\",\"이수한약\",\"여름한약\"],\"description\":null}, \"useServiceData\": \"false\"}}'></script>\n                </div>                <div class=\"se-component se-text se-l-default\" id=\"SE-3d8de0e5-5a01-48dd-a38e-0bd66751ed1c\">\n                    <div class=\"se-component-content\">\n                        <div class=\"se-section se-section-text se-l-default\">\n                            <div class=\"se-module se-module-text\">\n                                    <!-- SE-TEXT { --><p class=\"se-text-paragraph se-text-paragraph-align- \" style=\"\" id=\"SE-AA63F5BF-A333-4529-B447-2D1E621C1ABD\"><span style=\"\" class=\"se-fs- se-ff-   \" id=\"SE-F4E2FA8A-E85B-485C-80F1-9EC3BD43C6AC\">​</span></p><!-- } SE-TEXT -->\n                            </div>\n                        </div>\n                    </div>\n                </div>                <div class=\"se-component se-horizontalLine se-l-line6\" id=\"SE-49ad93d7-5586-4117-a083-63b100fe11ae\">\n                    <div class=\"se-component-content\">\n                        <div class=\"se-section se-section-horizontalLine se-l-line6 se-section-align-center\">\n                            <div class=\"se-module se-module-horizontalLine\">\n                                <hr class=\"se-hr\" />\n                            </div>\n                        </div>\n                    </div>\n                </div>                <div class=\"se-component se-text se-l-default\" id=\"SE-3fb32846-11d3-4545-985e-7346f63de5bd\">\n                    <div class=\"se-component-content\">\n                        <div class=\"se-section se-section-text se-l-default\">\n                            <div class=\"se-module se-module-text\">\n                                    <!-- SE-TEXT { --><p class=\"se-text-paragraph se-text-paragraph-align- \" style=\"\" id=\"SE-8C89F2CF-C345-4CB8-A4A8-54332DF03EB9\"><span style=\"\" class=\"se-fs- se-ff-   \" id=\"SE-5DE53ACB-1D4E-4F28-869F-80E43BE5B6E3\">​</span></p><!-- } SE-TEXT -->\n                            </div>\n                        </div>\n                    </div>\n                </div>                <div class=\"se-component se-image se-l-default\" id=\"SE-8a9f89e1-e0a6-4e21-a03e-5408712baf4c\">\n                    <div class=\"se-component-content se-component-content-fit\">\n                        <div class=\"se-section se-section-image se-l-default se-section-align-center\" >\n                                <div class=\"se-module se-module-image\" style=\"\">\n                                    <a href=\"#\" class=\"se-module-image-link-use se-module-image-link __se_image_link __se_link\" style=\"\" onclick=\"return false;\" data-linktype=\"img\" data-linkdata='{\"id\" : \"SE-8a9f89e1-e0a6-4e21-a03e-5408712baf4c\", \"src\" : \"https://isuhani-clinic-data.s3.ap-northeast-2.amazonaws.com/images/legacy/c3b0acef5ab0f802.png\", \"originalWidth\" : \"900\", \"originalHeight\" : \"400\", \"linkUse\" : \"true\", \"link\" : \"https://m.booking.naver.com/booking/13/bizes/331349?theme&#x3D;place&amp;entry&#x3D;pll&amp;area&#x3D;pll\"}'>\n                                        <img src=\"https://isuhani-clinic-data.s3.ap-northeast-2.amazonaws.com/images/legacy/c3b0acef5ab0f802.png\" data-lazy-src=\"https://isuhani-clinic-data.s3.ap-northeast-2.amazonaws.com/images/legacy/c3b0acef5ab0f802.png\" data-width=\"500\" data-height=\"222\" alt=\"\" class=\"se-image-resource\" />\n                                    </a>\n                                </div>\n                        </div>\n                    </div>\n                </div>\n                <div class=\"se-component se-image se-l-default\" id=\"SE-f0be88c7-e34e-4d40-a65b-0b36441519ad\">\n                    <div class=\"se-component-content se-component-content-fit\">\n                        <div class=\"se-section se-section-image se-l-default se-section-align-center\" >\n                                <div class=\"se-module se-module-image\" style=\"\">\n                                    <a href=\"#\" class=\"se-module-image-link-use se-module-image-link __se_image_link __se_link\" style=\"\" onclick=\"return false;\" data-linktype=\"img\" data-linkdata='{\"id\" : \"SE-f0be88c7-e34e-4d40-a65b-0b36441519ad\", \"src\" : \"https://isuhani-clinic-data.s3.ap-northeast-2.amazonaws.com/images/legacy/dcee9b5d38f9011f.png\", \"originalWidth\" : \"901\", \"originalHeight\" : \"400\", \"linkUse\" : \"true\", \"link\" : \"https://isumedical.modoo.at\"}'>\n                                        <img src=\"https://isuhani-clinic-data.s3.ap-northeast-2.amazonaws.com/images/legacy/dcee9b5d38f9011f.png\" data-lazy-src=\"https://isuhani-clinic-data.s3.ap-northeast-2.amazonaws.com/images/legacy/dcee9b5d38f9011f.png\" data-width=\"500\" data-height=\"221\" alt=\"\" class=\"se-image-resource\" />\n                                    </a>\n                                </div>\n                            <div class=\"se-module se-module-text se-caption\"><p class=\"se-text-paragraph se-text-paragraph-align- \" style=\"\" id=\"SE-0D39A6C1-00DB-41B6-B264-953A86E0228A\"><span style=\"\" class=\"se-fs- se-ff-   \" id=\"SE-AA9649D5-2AFD-4072-9086-9DFE36B5974B\">위 배너를 클릭하시면 해당 페이지로 이동합니다.</span></p></div>\n                        </div>\n                    </div>\n                </div>\n                <div class=\"se-component se-text se-l-default\" id=\"SE-68e0c21c-b1cb-4303-9be3-7fb328844932\">\n                    <div class=\"se-component-content\">\n                        <div class=\"se-section se-section-text se-l-default\">\n                            <div class=\"se-module se-module-text\">\n                                    <!-- SE-TEXT { --><p class=\"se-text-paragraph se-text-paragraph-align- \" style=\"\" id=\"SE-14C1C9E8-6E70-45B1-8B21-9004F75C819D\"><span style=\"\" class=\"se-fs- se-ff-   \" id=\"SE-1E98CA7F-5710-4B55-8FDA-EC0B0DD33902\">​</span></p><!-- } SE-TEXT -->\n                            </div>\n                        </div>\n                    </div>\n                </div>                <div class=\"se-component se-horizontalLine se-l-line6\" id=\"SE-13b150b0-8f66-409c-b0c2-d78acbeb46fd\">\n                    <div class=\"se-component-content\">\n                        <div class=\"se-section se-section-horizontalLine se-l-line6 se-section-align-center\">\n                            <div class=\"se-module se-module-horizontalLine\">\n                                <hr class=\"se-hr\" />\n                            </div>\n                        </div>\n                    </div>\n                </div>                <div class=\"se-component se-text se-l-default\" id=\"SE-e0ca1941-f9b6-43f7-9aff-e090ee02a314\">\n                    <div class=\"se-component-content\">\n                        <div class=\"se-section se-section-text se-l-default\">\n                            <div class=\"se-module se-module-text\">\n                                    <!-- SE-TEXT { --><p class=\"se-text-paragraph se-text-paragraph-align- \" style=\"\" id=\"SE-5AC7C430-C039-43F8-8612-674F04D1B34F\"><span style=\"\" class=\"se-fs- se-ff-   \" id=\"SE-05C791D8-27CB-4AAF-AD2D-A8740A677A78\">​</span></p><!-- } SE-TEXT -->\n                            </div>\n                        </div>\n                    </div>\n                </div>                <div class=\"se-component se-placesMap se-l-default\" id=\"SE-d1ac1db3-f058-4347-b442-943752e63b5c\">\n                    <div class=\"se-component-content\">\n                        <div class=\"se-section se-section-placesMap  se-section-align-center se-l-default\">\n                            <div class=\"se-module se-module-map-image\">\n                                <img src=\"https://simg.pstatic.net/static.map/v2/map/staticmap.bin?caller&#x3D;smarteditor&amp;markers&#x3D;color%3A0x11cc73%7Csize%3Amid%7Cpos%3A126.97218%2037.484026%7CviewSizeRatio%3A0.7%7Ctype%3Ad&amp;w&#x3D;848&amp;h&#x3D;452&amp;scale&#x3D;1&amp;dataversion&#x3D;168.47\" alt=\"\" class=\"se-map-image\" />\n                            </div>\n                                <div class=\"se-module se-module-map-text \">\n                                        <a href=\"#\" target=\"_blank\" class=\"se-map-info __se_link\" onclick=\"return false;\" data-linktype=\"map\" data-linkdata='{\"eventTarget\" : \"placeDesc\", \"placeId\" : \"13104608\", \"searchEngine\" : \"naver\", \"searchType\" : \"s\", \"name\" : \"이수한의원\", \"address\" : \"서울특별시 동작구 사당로 218-1 2층\", \"latitude\" : \"37.4840262\", \"longitude\" : \"126.9721803\", \"tel\" : \"0507-1344-1075\", \"bookingUrl\" : \"https://booking.naver.com/booking/13/bizes/331349\" }'>\n                                        <strong class=\"se-map-title\">이수한의원</strong>\n                                        <p class=\"se-map-address\">서울특별시 동작구 사당로 218-1 2층</p>\n                                    </a>\n                                </div>\n                        \n                        </div>\n                    </div>\n                    <script type=\"text/data\" class=\"__se_module_data\" data-module='{\"type\":\"v2_map\", \"id\" :\"SE-d1ac1db3-f058-4347-b442-943752e63b5c\", \"data\" : { \"layout\": \"default\", \"searchEngine\" : \"naver\", \"places\" : [{\"placeId\":\"13104608\",\"name\":\"이수한의원\",\"address\":\"서울특별시 동작구 사당로 218-1 2층\",\"latlng\":{\"@ctype\":\"position\",\"latitude\":37.4840262,\"longitude\":126.9721803},\"searchType\":\"s\",\"tel\":\"0507-1344-1075\",\"bookingUrl\":\"https://booking.naver.com/booking/13/bizes/331349\"}] }}'></script>\n                </div>                <div class=\"se-component se-text se-l-default\" id=\"SE-a27e45f3-6a27-4ba4-b061-4bdfaf3de98e\">\n                    <div class=\"se-component-content\">\n                        <div class=\"se-section se-section-text se-l-default\">\n                            <div class=\"se-module se-module-text\">\n                                    <!-- SE-TEXT { --><p class=\"se-text-paragraph se-text-paragraph-align- \" style=\"\" id=\"SE-96DAF1C9-53C4-4D97-8CA2-7E3494CCC843\"><span style=\"\" class=\"se-fs- se-ff-   \" id=\"SE-03778C41-D357-4F66-A51D-DCDA1650DEF1\">​</span></p><!-- } SE-TEXT -->\n                            </div>\n                        </div>\n                    </div>\n                </div>    </div>",
  "body_kind": "html",
  "images": [
    "https://isuhani-clinic-data.s3.ap-northeast-2.amazonaws.com/images/legacy/a6ee0bdf6a8a90dd.jpg",
    "https://isuhani-clinic-data.s3.ap-northeast-2.amazonaws.com/images/legacy/cdbbe3cd3894ff6e.jpg",
    "https://isuhani-clinic-data.s3.ap-northeast-2.amazonaws.com/images/legacy/cdbbe3cd3894ff6e.jpg",
    "https://isuhani-clinic-data.s3.ap-northeast-2.amazonaws.com/images/legacy/cdbbe3cd3894ff6e.jpg",
    "https://isuhani-clinic-data.s3.ap-northeast-2.amazonaws.com/images/legacy/08790c691a3151a2.jpg",
    "https://isuhani-clinic-data.s3.ap-northeast-2.amazonaws.com/images/legacy/08790c691a3151a2.jpg",
    "https://isuhani-clinic-data.s3.ap-northeast-2.amazonaws.com/images/legacy/08790c691a3151a2.jpg",
    "https://isuhani-clinic-data.s3.ap-northeast-2.amazonaws.com/images/legacy/d2ae9d628ad4d931.jpg",
    "https://isuhani-clinic-data.s3.ap-northeast-2.amazonaws.com/images/legacy/d2ae9d628ad4d931.jpg",
    "https://isuhani-clinic-data.s3.ap-northeast-2.amazonaws.com/images/legacy/d2ae9d628ad4d931.jpg",
    "https://isuhani-clinic-data.s3.ap-northeast-2.amazonaws.com/images/legacy/9831ec8d9561670e.jpg",
    "https://isuhani-clinic-data.s3.ap-northeast-2.amazonaws.com/images/legacy/9831ec8d9561670e.jpg",
    "https://isuhani-clinic-data.s3.ap-northeast-2.amazonaws.com/images/legacy/9831ec8d9561670e.jpg",
    "https://isuhani-clinic-data.s3.ap-northeast-2.amazonaws.com/images/legacy/7ca8823f4d49184e.jpg",
    "https://isuhani-clinic-data.s3.ap-northeast-2.amazonaws.com/images/legacy/7ca8823f4d49184e.jpg",
    "https://isuhani-clinic-data.s3.ap-northeast-2.amazonaws.com/images/legacy/7ca8823f4d49184e.jpg",
    "https://isuhani-clinic-data.s3.ap-northeast-2.amazonaws.com/images/legacy/dcee9b5d38f9011f.png",
    "https://isuhani-clinic-data.s3.ap-northeast-2.amazonaws.com/images/legacy/dcee9b5d38f9011f.png",
    "https://isuhani-clinic-data.s3.ap-northeast-2.amazonaws.com/images/legacy/dcee9b5d38f9011f.png",
    "https://isuhani-clinic-data.s3.ap-northeast-2.amazonaws.com/images/legacy/c9c3191abac6f074.jpg",
    "https://isuhani-clinic-data.s3.ap-northeast-2.amazonaws.com/images/legacy/c3b0acef5ab0f802.png",
    "https://isuhani-clinic-data.s3.ap-northeast-2.amazonaws.com/images/legacy/c3b0acef5ab0f802.png",
    "https://isuhani-clinic-data.s3.ap-northeast-2.amazonaws.com/images/legacy/c3b0acef5ab0f802.png",
    "https://isuhani-clinic-data.s3.ap-northeast-2.amazonaws.com/images/legacy/d721f1ec30328972.png",
    "https://isuhani-clinic-data.s3.ap-northeast-2.amazonaws.com/images/legacy/d721f1ec30328972.png",
    "https://isuhani-clinic-data.s3.ap-northeast-2.amazonaws.com/images/legacy/d721f1ec30328972.png"
  ],
  "meta": {
    "ogTitle": "이수역 한의원 여름 보약, 생맥산",
    "ogDesc": "이수한의원 남성역 1번 출구 | 일요일 진료 생맥산이 뭘까? 무더운 여름철, 더위로 힘들 때 음료처럼 복용...",
    "ogImage": "https://isuhani-clinic-data.s3.ap-northeast-2.amazonaws.com/images/legacy/c9c3191abac6f074.jpg",
    "category": "한의원 story",
    "date": "2023-07-14"
  }
}